{
"meta":{"test_sets":[],"test_metrics":[],"learn_metrics":[{"best_value":"Min","name":"Logloss"}],"launch_mode":"Train","parameters":"","iteration_count":900,"learn_sets":["learn"],"name":"experiment"},
"iterations":[
{"learn":[0.6780851172],"iteration":0,"passed_time":0.002868160793,"remaining_time":2.578476553},
{"learn":[0.6659478699],"iteration":1,"passed_time":0.005572429815,"remaining_time":2.502020987},
{"learn":[0.6539961568],"iteration":2,"passed_time":0.008399651858,"remaining_time":2.511495906},
{"learn":[0.6438363105],"iteration":3,"passed_time":0.0112060952,"remaining_time":2.510165325},
{"learn":[0.6334310781],"iteration":4,"passed_time":0.0137761677,"remaining_time":2.465934018},
{"learn":[0.6258824801],"iteration":5,"passed_time":0.01653924207,"remaining_time":2.464347068},
{"learn":[0.6165755386],"iteration":6,"passed_time":0.01927579416,"remaining_time":2.459040598},
{"learn":[0.6090107766],"iteration":7,"passed_time":0.02179359835,"remaining_time":2.429986217},
{"learn":[0.5998593622],"iteration":8,"passed_time":0.02421867103,"remaining_time":2.397648432},
{"learn":[0.5898421198],"iteration":9,"passed_time":0.02673234665,"remaining_time":2.379178852},
{"learn":[0.5820959416],"iteration":10,"passed_time":0.02918207388,"remaining_time":2.358442153},
{"learn":[0.5759620467],"iteration":11,"passed_time":0.03190726562,"remaining_time":2.361137656},
{"learn":[0.5688390892],"iteration":12,"passed_time":0.03492813718,"remaining_time":2.383173668},
{"learn":[0.5641786772],"iteration":13,"passed_time":0.03762424871,"remaining_time":2.381077454},
{"learn":[0.5586787877],"iteration":14,"passed_time":0.04013581657,"remaining_time":2.368013178},
{"learn":[0.5536285272],"iteration":15,"passed_time":0.04281326893,"remaining_time":2.365433108},
{"learn":[0.5486734007],"iteration":16,"passed_time":0.04565343101,"remaining_time":2.371292917},
{"learn":[0.5440214942],"iteration":17,"passed_time":0.04856786019,"remaining_time":2.379825149},
{"learn":[0.5389889053],"iteration":18,"passed_time":0.05125672363,"remaining_time":2.376693343},
{"learn":[0.5343479707],"iteration":19,"passed_time":0.05385429484,"remaining_time":2.369588973},
{"learn":[0.5302127016],"iteration":20,"passed_time":0.0564561794,"remaining_time":2.363094366},
{"learn":[0.5252897749],"iteration":21,"passed_time":0.05921737699,"remaining_time":2.363311682},
{"learn":[0.5221167434],"iteration":22,"passed_time":0.0616952877,"remaining_time":2.352468144},
{"learn":[0.5193143778],"iteration":23,"passed_time":0.06419736476,"remaining_time":2.343203814},
{"learn":[0.5157170277],"iteration":24,"passed_time":0.06656314386,"remaining_time":2.329710035},
{"learn":[0.5133503328],"iteration":25,"passed_time":0.06893623718,"remaining_time":2.317318127},
{"learn":[0.5102210846],"iteration":26,"passed_time":0.07167351571,"remaining_time":2.317443675},
{"learn":[0.5073754044],"iteration":27,"passed_time":0.07483833366,"remaining_time":2.330679534},
{"learn":[0.5048007339],"iteration":28,"passed_time":0.07808525103,"remaining_time":2.345250126},
{"learn":[0.5023736228],"iteration":29,"passed_time":0.08081351972,"remaining_time":2.343592072},
{"learn":[0.5000415855],"iteration":30,"passed_time":0.08439577759,"remaining_time":2.365804217},
{"learn":[0.4976222641],"iteration":31,"passed_time":0.08698135078,"remaining_time":2.35936914},
{"learn":[0.4949403309],"iteration":32,"passed_time":0.08949042139,"remaining_time":2.351157435},
{"learn":[0.4922907968],"iteration":33,"passed_time":0.09185445777,"remaining_time":2.339587071},
{"learn":[0.4903190322],"iteration":34,"passed_time":0.09448008747,"remaining_time":2.335007876},
{"learn":[0.4880570825],"iteration":35,"passed_time":0.0969374242,"remaining_time":2.326498181},
{"learn":[0.4857445928],"iteration":36,"passed_time":0.09917256923,"remaining_time":2.313133169},
{"learn":[0.4836568456],"iteration":37,"passed_time":0.1016599454,"remaining_time":2.306075603},
{"learn":[0.4817694428],"iteration":38,"passed_time":0.1039404403,"remaining_time":2.294685106},
{"learn":[0.4799394256],"iteration":39,"passed_time":0.1063881667,"remaining_time":2.287345584},
{"learn":[0.477261906],"iteration":40,"passed_time":0.1089112072,"remaining_time":2.28182261},
{"learn":[0.4748407621],"iteration":41,"passed_time":0.1118063088,"remaining_time":2.284043165},
{"learn":[0.4727779418],"iteration":42,"passed_time":0.1146995906,"remaining_time":2.285989515},
{"learn":[0.4714566842],"iteration":43,"passed_time":0.1174412006,"remaining_time":2.284765175},
{"learn":[0.4704078391],"iteration":44,"passed_time":0.1200184025,"remaining_time":2.280349648},
{"learn":[0.4692935363],"iteration":45,"passed_time":0.1226655002,"remaining_time":2.277311678},
{"learn":[0.4674489708],"iteration":46,"passed_time":0.1250452991,"remaining_time":2.269439151},
{"learn":[0.4659946436],"iteration":47,"passed_time":0.1274939475,"remaining_time":2.263017568},
{"learn":[0.4638492825],"iteration":48,"passed_time":0.1301565984,"remaining_time":2.260474801},
{"learn":[0.4627386481],"iteration":49,"passed_time":0.1326622751,"remaining_time":2.255258676},
{"learn":[0.4612858635],"iteration":50,"passed_time":0.1348867047,"remaining_time":2.245466907},
{"learn":[0.4600989639],"iteration":51,"passed_time":0.1372025406,"remaining_time":2.237456816},
{"learn":[0.4590430222],"iteration":52,"passed_time":0.1394488956,"remaining_time":2.228551219},
{"learn":[0.458148591],"iteration":53,"passed_time":0.1420745335,"remaining_time":2.225834358},
{"learn":[0.456887795],"iteration":54,"passed_time":0.1446069906,"remaining_time":2.221689219},
{"learn":[0.4558703992],"iteration":55,"passed_time":0.1468272128,"remaining_time":2.21289585},
{"learn":[0.4548164167],"iteration":56,"passed_time":0.1490421942,"remaining_time":2.204255608},
{"learn":[0.4538409238],"iteration":57,"passed_time":0.151292127,"remaining_time":2.196344327},
{"learn":[0.4530105356],"iteration":58,"passed_time":0.1535638232,"remaining_time":2.188935174},
{"learn":[0.4516959582],"iteration":59,"passed_time":0.1556775731,"remaining_time":2.179486024},
{"learn":[0.4507605979],"iteration":60,"passed_time":0.1579399624,"remaining_time":2.172321777},
{"learn":[0.4498809797],"iteration":61,"passed_time":0.1601859922,"remaining_time":2.16509454},
{"learn":[0.4489145967],"iteration":62,"passed_time":0.162347948,"remaining_time":2.156908452},
{"learn":[0.4480868073],"iteration":63,"passed_time":0.1645902641,"remaining_time":2.149960325},
{"learn":[0.4468606472],"iteration":64,"passed_time":0.1670949399,"remaining_time":2.146527305},
{"learn":[0.4459950399],"iteration":65,"passed_time":0.1693686931,"remaining_time":2.140204394},
{"learn":[0.4446729075],"iteration":66,"passed_time":0.1715838003,"remaining_time":2.133273219},
{"learn":[0.4441805225],"iteration":67,"passed_time":0.1738263692,"remaining_time":2.126816752},
{"learn":[0.4431836732],"iteration":68,"passed_time":0.1760624979,"remaining_time":2.120404866},
{"learn":[0.4426834897],"iteration":69,"passed_time":0.1784359445,"remaining_time":2.115740484},
{"learn":[0.4420281932],"iteration":70,"passed_time":0.1805494825,"remaining_time":2.108105929},
{"learn":[0.4408673099],"iteration":71,"passed_time":0.1827211691,"remaining_time":2.101293445},
{"learn":[0.4395270008],"iteration":72,"passed_time":0.1849964051,"remaining_time":2.095781192},
{"learn":[0.438982368],"iteration":73,"passed_time":0.1873004332,"remaining_time":2.090677809},
{"learn":[0.4379939187],"iteration":74,"passed_time":0.1894103997,"remaining_time":2.083514397},
{"learn":[0.4371490652],"iteration":75,"passed_time":0.1916050997,"remaining_time":2.07740266},
{"learn":[0.4364637521],"iteration":76,"passed_time":0.1936951172,"remaining_time":2.070273785},
{"learn":[0.4354250523],"iteration":77,"passed_time":0.1958829911,"remaining_time":2.064305368},
{"learn":[0.4344404531],"iteration":78,"passed_time":0.1980414533,"remaining_time":2.058127002},
{"learn":[0.4338456771],"iteration":79,"passed_time":0.2002045477,"remaining_time":2.052096614},
{"learn":[0.4334061476],"iteration":80,"passed_time":0.2023009972,"remaining_time":2.04548786},
{"learn":[0.4328394479],"iteration":81,"passed_time":0.2044015671,"remaining_time":2.039030266},
{"learn":[0.4320301092],"iteration":82,"passed_time":0.2064440734,"remaining_time":2.03210612},
{"learn":[0.430991745],"iteration":83,"passed_time":0.2084731008,"remaining_time":2.025167265},
{"learn":[0.4304552868],"iteration":84,"passed_time":0.2106541669,"remaining_time":2.019801718},
{"learn":[0.4299452623],"iteration":85,"passed_time":0.2128378443,"remaining_time":2.014534945},
{"learn":[0.4294251435],"iteration":86,"passed_time":0.2148524326,"remaining_time":2.007758939},
{"learn":[0.428956123],"iteration":87,"passed_time":0.2169904431,"remaining_time":2.002229998},
{"learn":[0.4284592878],"iteration":88,"passed_time":0.2191222191,"remaining_time":1.996720446},
{"learn":[0.4275396183],"iteration":89,"passed_time":0.2209920222,"remaining_time":1.9889282},
{"learn":[0.4271258567],"iteration":90,"passed_time":0.2228518064,"remaining_time":1.981177048},
{"learn":[0.4267515573],"iteration":91,"passed_time":0.224884014,"remaining_time":1.975068297},
{"learn":[0.4260901751],"iteration":92,"passed_time":0.2269414015,"remaining_time":1.96926571},
{"learn":[0.4254541045],"iteration":93,"passed_time":0.228901506,"remaining_time":1.962708657},
{"learn":[0.4249933523],"iteration":94,"passed_time":0.2310724064,"remaining_time":1.958034602},
{"learn":[0.4241780619],"iteration":95,"passed_time":0.2331087054,"remaining_time":1.952285408},
{"learn":[0.4232076597],"iteration":96,"passed_time":0.2351467671,"remaining_time":1.946627361},
{"learn":[0.4228259582],"iteration":97,"passed_time":0.2370677081,"remaining_time":1.940084713},
{"learn":[0.4222725741],"iteration":98,"passed_time":0.2389865486,"remaining_time":1.933618439},
{"learn":[0.4218256732],"iteration":99,"passed_time":0.240959075,"remaining_time":1.9276726},
{"learn":[0.4214513209],"iteration":100,"passed_time":0.242962321,"remaining_time":1.92204846},
{"learn":[0.4210329836],"iteration":101,"passed_time":0.2447226863,"remaining_time":1.914595134},
{"learn":[0.4206772633],"iteration":102,"passed_time":0.2466608563,"remaining_time":1.908628179},
{"learn":[0.4202689146],"iteration":103,"passed_time":0.2484600453,"remaining_time":1.901674962},
{"learn":[0.4199264167],"iteration":104,"passed_time":0.250310269,"remaining_time":1.895206323},
{"learn":[0.419461167],"iteration":105,"passed_time":0.2522515503,"remaining_time":1.889506896},
{"learn":[0.4189901503],"iteration":106,"passed_time":0.2541836089,"remaining_time":1.883809363},
{"learn":[0.4185028817],"iteration":107,"passed_time":0.2561738443,"remaining_time":1.878608191},
{"learn":[0.4181223614],"iteration":108,"passed_time":0.2580535576,"remaining_time":1.872663891},
{"learn":[0.4177086887],"iteration":109,"passed_time":0.2598777771,"remaining_time":1.866394945},
{"learn":[0.4173538184],"iteration":110,"passed_time":0.2616991344,"remaining_time":1.860185739},
{"learn":[0.4168724993],"iteration":111,"passed_time":0.2636452969,"remaining_time":1.854932982},
{"learn":[0.4165397442],"iteration":112,"passed_time":0.2655138764,"remaining_time":1.849198413},
{"learn":[0.4161924472],"iteration":113,"passed_time":0.2674103268,"remaining_time":1.843723832},
{"learn":[0.4157379071],"iteration":114,"passed_time":0.2693891393,"remaining_time":1.83887369},
{"learn":[0.4153197937],"iteration":115,"passed_time":0.2713461785,"remaining_time":1.833925896},
{"learn":[0.4145246811],"iteration":116,"passed_time":0.2731687459,"remaining_time":1.828129299},
{"learn":[0.4142291971],"iteration":117,"passed_time":0.2749961936,"remaining_time":1.822432402},
{"learn":[0.4137151544],"iteration":118,"passed_time":0.2771856309,"remaining_time":1.819176284},
{"learn":[0.4130929038],"iteration":119,"passed_time":0.2791829658,"remaining_time":1.814689278},
{"learn":[0.4127496617],"iteration":120,"passed_time":0.2810360663,"remaining_time":1.80931484},
{"learn":[0.4120377517],"iteration":121,"passed_time":0.2829468154,"remaining_time":1.804365757},
{"learn":[0.4114613377],"iteration":122,"passed_time":0.2848001939,"remaining_time":1.799103664},
{"learn":[0.4109627907],"iteration":123,"passed_time":0.2866516314,"remaining_time":1.793884403},
{"learn":[0.4105804933],"iteration":124,"passed_time":0.2886456855,"remaining_time":1.78960325},
{"learn":[0.4103389341],"iteration":125,"passed_time":0.2905196634,"remaining_time":1.784620789},
{"learn":[0.4099499199],"iteration":126,"passed_time":0.2926271299,"remaining_time":1.781108436},
{"learn":[0.4096884514],"iteration":127,"passed_time":0.2945202434,"remaining_time":1.776325218},
{"learn":[0.4093649014],"iteration":128,"passed_time":0.2966412451,"remaining_time":1.772948837},
{"learn":[0.4092058808],"iteration":129,"passed_time":0.2984214371,"remaining_time":1.767573128},
{"learn":[0.4087949301],"iteration":130,"passed_time":0.3004086154,"remaining_time":1.763467369},
{"learn":[0.4084185977],"iteration":131,"passed_time":0.3022390097,"remaining_time":1.758481511},
{"learn":[0.4081004191],"iteration":132,"passed_time":0.304137393,"remaining_time":1.753935191},
{"learn":[0.4078911953],"iteration":133,"passed_time":0.3060688946,"remaining_time":1.749617711},
{"learn":[0.4075097396],"iteration":134,"passed_time":0.3080843597,"remaining_time":1.745811371},
{"learn":[0.4071419685],"iteration":135,"passed_time":0.3099081779,"remaining_time":1.740954764},
{"learn":[0.4066046215],"iteration":136,"passed_time":0.3118076962,"remaining_time":1.736564031},
{"learn":[0.4061835633],"iteration":137,"passed_time":0.3136632966,"remaining_time":1.731966899},
{"learn":[0.4059567636],"iteration":138,"passed_time":0.3155258408,"remaining_time":1.727447229},
{"learn":[0.4056467978],"iteration":139,"passed_time":0.3173151079,"remaining_time":1.722567729},
{"learn":[0.4053771471],"iteration":140,"passed_time":0.3191617148,"remaining_time":1.71804072},
{"learn":[0.4048882436],"iteration":141,"passed_time":0.3211145593,"remaining_time":1.714118563},
{"learn":[0.4044034605],"iteration":142,"passed_time":0.3229901196,"remaining_time":1.709814829},
{"learn":[0.403797337],"iteration":143,"passed_time":0.3248762224,"remaining_time":1.705600167},
{"learn":[0.403447121],"iteration":144,"passed_time":0.3266986176,"remaining_time":1.701085906},
{"learn":[0.4029439394],"iteration":145,"passed_time":0.328541749,"remaining_time":1.696715608},
{"learn":[0.4027397569],"iteration":146,"passed_time":0.3305118687,"remaining_time":1.693030185},
{"learn":[0.4025037687],"iteration":147,"passed_time":0.3323886255,"remaining_time":1.688893557},
{"learn":[0.4023416121],"iteration":148,"passed_time":0.3342581026,"remaining_time":1.684750571},
{"learn":[0.4020861352],"iteration":149,"passed_time":0.3361585212,"remaining_time":1.680792606},
{"learn":[0.4018325748],"iteration":150,"passed_time":0.338082329,"remaining_time":1.67697791},
{"learn":[0.4015817675],"iteration":151,"passed_time":0.3400373538,"remaining_time":1.673341715},
{"learn":[0.4011254429],"iteration":152,"passed_time":0.3418690397,"remaining_time":1.669125312},
{"learn":[0.4009860099],"iteration":153,"passed_time":0.3436573829,"remaining_time":1.66472992},
{"learn":[0.4007594971],"iteration":154,"passed_time":0.3455948074,"remaining_time":1.661084719},
{"learn":[0.4004612206],"iteration":155,"passed_time":0.3474460999,"remaining_time":1.65705063},
{"learn":[0.4002215345],"iteration":156,"passed_time":0.3492701356,"remaining_time":1.652915355},
{"learn":[0.3996646944],"iteration":157,"passed_time":0.3511640507,"remaining_time":1.649137504},
{"learn":[0.3995290452],"iteration":158,"passed_time":0.3529444193,"remaining_time":1.644854181},
{"learn":[0.3992805777],"iteration":159,"passed_time":0.3547860589,"remaining_time":1.640885522},
{"learn":[0.3989842198],"iteration":160,"passed_time":0.3567036503,"remaining_time":1.63729191},
{"learn":[0.3986780494],"iteration":161,"passed_time":0.3586953567,"remaining_time":1.634056625},
{"learn":[0.3979688194],"iteration":162,"passed_time":0.360614776,"remaining_time":1.630509754},
{"learn":[0.3976843223],"iteration":163,"passed_time":0.362589853,"remaining_time":1.627232511},
{"learn":[0.3974795769],"iteration":164,"passed_time":0.3645553278,"remaining_time":1.623928278},
{"learn":[0.3971968751],"iteration":165,"passed_time":0.3665016534,"remaining_time":1.620555504},
{"learn":[0.3969626477],"iteration":166,"passed_time":0.3685887597,"remaining_time":1.61781773},
{"learn":[0.3965837205],"iteration":167,"passed_time":0.3710905859,"remaining_time":1.616894696},
{"learn":[0.3963437223],"iteration":168,"passed_time":0.3734043195,"remaining_time":1.615139394},
{"learn":[0.3960366204],"iteration":169,"passed_time":0.3755974443,"remaining_time":1.612859614},
{"learn":[0.3955355254],"iteration":170,"passed_time":0.3776543264,"remaining_time":1.610000023},
{"learn":[0.3953729912],"iteration":171,"passed_time":0.379982779,"remaining_time":1.608299204},
{"learn":[0.3951388338],"iteration":172,"passed_time":0.3821771112,"remaining_time":1.606027513},
{"learn":[0.3944624398],"iteration":173,"passed_time":0.3840977161,"remaining_time":1.602614609},
{"learn":[0.3939582107],"iteration":174,"passed_time":0.3861516689,"remaining_time":1.5997712},
{"learn":[0.3938245405],"iteration":175,"passed_time":0.3879964833,"remaining_time":1.596076442},
{"learn":[0.3933960159],"iteration":176,"passed_time":0.3898629821,"remaining_time":1.592491164},
{"learn":[0.3928457603],"iteration":177,"passed_time":0.3919066415,"remaining_time":1.589643793},
{"learn":[0.3926932844],"iteration":178,"passed_time":0.3938711408,"remaining_time":1.58648655},
{"learn":[0.3925240774],"iteration":179,"passed_time":0.3958530429,"remaining_time":1.583412172},
{"learn":[0.3920480101],"iteration":180,"passed_time":0.3977004886,"remaining_time":1.579815753},
{"learn":[0.3919082827],"iteration":181,"passed_time":0.3996361631,"remaining_time":1.576586621},
{"learn":[0.3914038819],"iteration":182,"passed_time":0.4015537536,"remaining_time":1.573300772},
{"learn":[0.3912370899],"iteration":183,"passed_time":0.4033969973,"remaining_time":1.56974049},
{"learn":[0.3907086132],"iteration":184,"passed_time":0.4052766264,"remaining_time":1.566339394},
{"learn":[0.3904746076],"iteration":185,"passed_time":0.4072923804,"remaining_time":1.563477202},
{"learn":[0.3902179721],"iteration":186,"passed_time":0.4092337777,"remaining_time":1.560340553},
{"learn":[0.3897571401],"iteration":187,"passed_time":0.4110894478,"remaining_time":1.556891951},
{"learn":[0.3895690951],"iteration":188,"passed_time":0.412972124,"remaining_time":1.5535618},
{"learn":[0.3893761841],"iteration":189,"passed_time":0.4148197363,"remaining_time":1.550115857},
{"learn":[0.3891281389],"iteration":190,"passed_time":0.4167630991,"remaining_time":1.54704208},
{"learn":[0.3889481842],"iteration":191,"passed_time":0.418690598,"remaining_time":1.54392158},
{"learn":[0.3882892667],"iteration":192,"passed_time":0.4207333426,"remaining_time":1.541235612},
{"learn":[0.3878511046],"iteration":193,"passed_time":0.422690486,"remaining_time":1.538244758},
{"learn":[0.3875106343],"iteration":194,"passed_time":0.4245398329,"remaining_time":1.53487478},
{"learn":[0.3873287067],"iteration":195,"passed_time":0.4265024191,"remaining_time":1.531927056},
{"learn":[0.3869241377],"iteration":196,"passed_time":0.4284613714,"remaining_time":1.528976366},
{"learn":[0.386437129],"iteration":197,"passed_time":0.4304426051,"remaining_time":1.526114691},
{"learn":[0.3862293383],"iteration":198,"passed_time":0.4324873994,"remaining_time":1.523485764},
{"learn":[0.3860846408],"iteration":199,"passed_time":0.4344549059,"remaining_time":1.520592171},
{"learn":[0.3859755502],"iteration":200,"passed_time":0.4365226266,"remaining_time":1.518056299},
{"learn":[0.3856457887],"iteration":201,"passed_time":0.4384242482,"remaining_time":1.514951115},
{"learn":[0.3853079385],"iteration":202,"passed_time":0.4404141121,"remaining_time":1.512160769},
{"learn":[0.3851812581],"iteration":203,"passed_time":0.4425229727,"remaining_time":1.50978426},
{"learn":[0.3848464024],"iteration":204,"passed_time":0.4444560304,"remaining_time":1.506814347},
{"learn":[0.3844534483],"iteration":205,"passed_time":0.4463266895,"remaining_time":1.503644284},
{"learn":[0.3842685283],"iteration":206,"passed_time":0.4482800784,"remaining_time":1.500763741},
{"learn":[0.3839593979],"iteration":207,"passed_time":0.4500334538,"remaining_time":1.497226683},
{"learn":[0.3838381361],"iteration":208,"passed_time":0.4518882118,"remaining_time":1.494041887},
{"learn":[0.383650029],"iteration":209,"passed_time":0.4537999953,"remaining_time":1.491057128},
{"learn":[0.3832944511],"iteration":210,"passed_time":0.4557666966,"remaining_time":1.488261867},
{"learn":[0.3831773162],"iteration":211,"passed_time":0.4578388375,"remaining_time":1.485816605},
{"learn":[0.3828915215],"iteration":212,"passed_time":0.4598202469,"remaining_time":1.483082205},
{"learn":[0.3827653287],"iteration":213,"passed_time":0.4617247207,"remaining_time":1.480108217},
{"learn":[0.382550115],"iteration":214,"passed_time":0.4636915678,"remaining_time":1.477342902},
{"learn":[0.3824183381],"iteration":215,"passed_time":0.4659922781,"remaining_time":1.475642214},
{"learn":[0.3822834398],"iteration":216,"passed_time":0.4681694493,"remaining_time":1.473547161},
{"learn":[0.3819229253],"iteration":217,"passed_time":0.4704684865,"remaining_time":1.471832605},
{"learn":[0.3816957278],"iteration":218,"passed_time":0.4728146781,"remaining_time":1.470259341},
{"learn":[0.3815216086],"iteration":219,"passed_time":0.4750361593,"remaining_time":1.468293583},
{"learn":[0.3813467519],"iteration":220,"passed_time":0.4772685453,"remaining_time":1.466359015},
{"learn":[0.3812448664],"iteration":221,"passed_time":0.4794931651,"remaining_time":1.464398045},
{"learn":[0.3811142813],"iteration":222,"passed_time":0.4820249972,"remaining_time":1.463367368},
{"learn":[0.380614077],"iteration":223,"passed_time":0.4843032141,"remaining_time":1.461557914},
{"learn":[0.3804939142],"iteration":224,"passed_time":0.4865556895,"remaining_time":1.459667069},
{"learn":[0.3800613108],"iteration":225,"passed_time":0.4888806413,"remaining_time":1.457989169},
{"learn":[0.3799482219],"iteration":226,"passed_time":0.4912137379,"remaining_time":1.456329716},
{"learn":[0.3797082853],"iteration":227,"passed_time":0.4933368826,"remaining_time":1.454045549},
{"learn":[0.3795186177],"iteration":228,"passed_time":0.4955828011,"remaining_time":1.452122531},
{"learn":[0.3793366523],"iteration":229,"passed_time":0.4975927843,"remaining_time":1.449509415},
{"learn":[0.3791564081],"iteration":230,"passed_time":0.5000341385,"remaining_time":1.448150817},
{"learn":[0.3790764949],"iteration":231,"passed_time":0.5021493178,"remaining_time":1.445843725},
{"learn":[0.3789167116],"iteration":232,"passed_time":0.5043294907,"remaining_time":1.443724336},
{"learn":[0.3786739369],"iteration":233,"passed_time":0.5065932712,"remaining_time":1.441842387},
{"learn":[0.3785158734],"iteration":234,"passed_time":0.5086225278,"remaining_time":1.439293536},
{"learn":[0.3782813075],"iteration":235,"passed_time":0.5106769887,"remaining_time":1.436820002},
{"learn":[0.3781057489],"iteration":236,"passed_time":0.5125949135,"remaining_time":1.433968049},
{"learn":[0.3779685423],"iteration":237,"passed_time":0.5145825537,"remaining_time":1.43131786},
{"learn":[0.3775219236],"iteration":238,"passed_time":0.5168679834,"remaining_time":1.429496808},
{"learn":[0.3773839147],"iteration":239,"passed_time":0.5188204167,"remaining_time":1.426756146},
{"learn":[0.3772238542],"iteration":240,"passed_time":0.5208633515,"remaining_time":1.424269497},
{"learn":[0.3771568474],"iteration":241,"passed_time":0.5232055567,"remaining_time":1.422600233},
{"learn":[0.3767910214],"iteration":242,"passed_time":0.5256120889,"remaining_time":1.421099351},
{"learn":[0.3765922453],"iteration":243,"passed_time":0.5279061968,"remaining_time":1.419288792},
{"learn":[0.3763852138],"iteration":244,"passed_time":0.5301209373,"remaining_time":1.417262098},
{"learn":[0.3761965312],"iteration":245,"passed_time":0.5322644631,"remaining_time":1.415044548},
{"learn":[0.3759593218],"iteration":246,"passed_time":0.5344419169,"remaining_time":1.412917294},
{"learn":[0.3758714491],"iteration":247,"passed_time":0.5365953493,"remaining_time":1.410726483},
{"learn":[0.3755714961],"iteration":248,"passed_time":0.5388131213,"remaining_time":1.408704185},
{"learn":[0.3754145182],"iteration":249,"passed_time":0.5409904166,"remaining_time":1.406575083},
{"learn":[0.3752531838],"iteration":250,"passed_time":0.5430041707,"remaining_time":1.404022736},
{"learn":[0.3751309904],"iteration":251,"passed_time":0.5450761748,"remaining_time":1.40162445},
{"learn":[0.3748278615],"iteration":252,"passed_time":0.5472934541,"remaining_time":1.399600256},
{"learn":[0.3747158801],"iteration":253,"passed_time":0.5494140011,"remaining_time":1.397328523},
{"learn":[0.3745886112],"iteration":254,"passed_time":0.5514320341,"remaining_time":1.394798674},
{"learn":[0.3744184916],"iteration":255,"passed_time":0.5534915973,"remaining_time":1.392377299},
{"learn":[0.3740984511],"iteration":256,"passed_time":0.5558995126,"remaining_time":1.390830298},
{"learn":[0.3739386387],"iteration":257,"passed_time":0.5582721358,"remaining_time":1.389188803},
{"learn":[0.3738260116],"iteration":258,"passed_time":0.5603299001,"remaining_time":1.386762417},
{"learn":[0.3737003225],"iteration":259,"passed_time":0.5625428888,"remaining_time":1.384720957},
{"learn":[0.3735204653],"iteration":260,"passed_time":0.5645664597,"remaining_time":1.382214436},
{"learn":[0.3733155301],"iteration":261,"passed_time":0.5672413387,"remaining_time":1.381297611},
{"learn":[0.3731228102],"iteration":262,"passed_time":0.5694240778,"remaining_time":1.379175428},
{"learn":[0.3728957764],"iteration":263,"passed_time":0.5713860146,"remaining_time":1.376520853},
{"learn":[0.3725811472],"iteration":264,"passed_time":0.573342668,"remaining_time":1.373858846},
{"learn":[0.3724775621],"iteration":265,"passed_time":0.5753228799,"remaining_time":1.371258293},
{"learn":[0.3724002914],"iteration":266,"passed_time":0.5773865173,"remaining_time":1.36886017},
{"learn":[0.3722403925],"iteration":267,"passed_time":0.5794635142,"remaining_time":1.366496048},
{"learn":[0.3720551309],"iteration":268,"passed_time":0.5814368086,"remaining_time":1.363890804},
{"learn":[0.3717570508],"iteration":269,"passed_time":0.5834548932,"remaining_time":1.361394751},
{"learn":[0.3715775331],"iteration":270,"passed_time":0.5855684584,"remaining_time":1.359123839},
{"learn":[0.3713293808],"iteration":271,"passed_time":0.5876658753,"remaining_time":1.3568168},
{"learn":[0.3711536498],"iteration":272,"passed_time":0.5896144798,"remaining_time":1.35416952},
{"learn":[0.3709997514],"iteration":273,"passed_time":0.591690195,"remaining_time":1.351817745},
{"learn":[0.3708839556],"iteration":274,"passed_time":0.593961239,"remaining_time":1.349911907},
{"learn":[0.3707461207],"iteration":275,"passed_time":0.5960918293,"remaining_time":1.347685875},
{"learn":[0.370534627],"iteration":276,"passed_time":0.5982451811,"remaining_time":1.345511725},
{"learn":[0.3704194725],"iteration":277,"passed_time":0.6002565275,"remaining_time":1.34302},
{"learn":[0.3702328298],"iteration":278,"passed_time":0.6023904701,"remaining_time":1.340804595},
{"learn":[0.3701406194],"iteration":279,"passed_time":0.6045861837,"remaining_time":1.33872655},
{"learn":[0.3699734826],"iteration":280,"passed_time":0.6067218119,"remaining_time":1.336515308},
{"learn":[0.3697876684],"iteration":281,"passed_time":0.6090408906,"remaining_time":1.334706633},
{"learn":[0.3695280652],"iteration":282,"passed_time":0.6113934643,"remaining_time":1.332967376},
{"learn":[0.3693687087],"iteration":283,"passed_time":0.6136344009,"remaining_time":1.330981658},
{"learn":[0.3692997479],"iteration":284,"passed_time":0.6157511979,"remaining_time":1.328726269},
{"learn":[0.3689641155],"iteration":285,"passed_time":0.6177379487,"remaining_time":1.326192659},
{"learn":[0.3685909895],"iteration":286,"passed_time":0.6196737645,"remaining_time":1.323554068},
{"learn":[0.3684691756],"iteration":287,"passed_time":0.6216029581,"remaining_time":1.320906286},
{"learn":[0.3681255008],"iteration":288,"passed_time":0.62348357,"remaining_time":1.318160766},
{"learn":[0.3679509632],"iteration":289,"passed_time":0.625377447,"remaining_time":1.315449113},
{"learn":[0.3678320078],"iteration":290,"passed_time":0.6272898139,"remaining_time":1.312781775},
{"learn":[0.3677143751],"iteration":291,"passed_time":0.6291086377,"remaining_time":1.309924835},
{"learn":[0.367565551],"iteration":292,"passed_time":0.630909189,"remaining_time":1.307037125},
{"learn":[0.3674913131],"iteration":293,"passed_time":0.6327647242,"remaining_time":1.304270146},
{"learn":[0.3673137795],"iteration":294,"passed_time":0.6346643304,"remaining_time":1.301599728},
{"learn":[0.3670221824],"iteration":295,"passed_time":0.6366450088,"remaining_time":1.29909995},
{"learn":[0.3669222489],"iteration":296,"passed_time":0.6385879051,"remaining_time":1.296526959},
{"learn":[0.366751805],"iteration":297,"passed_time":0.6405473501,"remaining_time":1.293991627},
{"learn":[0.3665685127],"iteration":298,"passed_time":0.6423890558,"remaining_time":1.291223487},
{"learn":[0.3664506441],"iteration":299,"passed_time":0.6442285767,"remaining_time":1.288457153},
{"learn":[0.3662713636],"iteration":300,"passed_time":0.6461854095,"remaining_time":1.285930433},
{"learn":[0.3661683965],"iteration":301,"passed_time":0.6482858924,"remaining_time":1.283691933},
{"learn":[0.3659936629],"iteration":302,"passed_time":0.65015671,"remaining_time":1.281001835},
{"learn":[0.3658421023],"iteration":303,"passed_time":0.6520414984,"remaining_time":1.278344517},
{"learn":[0.3656740673],"iteration":304,"passed_time":0.6539461,"remaining_time":1.275730916},
{"learn":[0.3654099],"iteration":305,"passed_time":0.6558614532,"remaining_time":1.273142821},
{"learn":[0.3652485451],"iteration":306,"passed_time":0.6577349954,"remaining_time":1.270478346},
{"learn":[0.365228249],"iteration":307,"passed_time":0.6596956315,"remaining_time":1.267986409},
{"learn":[0.3651611638],"iteration":308,"passed_time":0.6615706303,"remaining_time":1.265334118},
{"learn":[0.3650304047],"iteration":309,"passed_time":0.6635470723,"remaining_time":1.262879912},
{"learn":[0.3649078046],"iteration":310,"passed_time":0.6657494587,"remaining_time":1.260856692},
{"learn":[0.3647723056],"iteration":311,"passed_time":0.6675608822,"remaining_time":1.258095509},
{"learn":[0.3646197134],"iteration":312,"passed_time":0.6694791584,"remaining_time":1.255540786},
{"learn":[0.3644127272],"iteration":313,"passed_time":0.6713816115,"remaining_time":1.252960587},
{"learn":[0.3642915851],"iteration":314,"passed_time":0.673258352,"remaining_time":1.250336939},
{"learn":[0.3641754184],"iteration":315,"passed_time":0.6751541874,"remaining_time":1.247753308},
{"learn":[0.3640772764],"iteration":316,"passed_time":0.6770820096,"remaining_time":1.245232844},
{"learn":[0.3639532585],"iteration":317,"passed_time":0.6790700865,"remaining_time":1.242826385},
{"learn":[0.3638628604],"iteration":318,"passed_time":0.6810101785,"remaining_time":1.240335153},
{"learn":[0.3637504799],"iteration":319,"passed_time":0.6829370597,"remaining_time":1.237823421},
{"learn":[0.3636840451],"iteration":320,"passed_time":0.6847426318,"remaining_time":1.235096523},
{"learn":[0.3635904867],"iteration":321,"passed_time":0.6866673554,"remaining_time":1.232589228},
{"learn":[0.3634886078],"iteration":322,"passed_time":0.6887030058,"remaining_time":1.230283698},
{"learn":[0.36318615],"iteration":323,"passed_time":0.6908073411,"remaining_time":1.22810194},
{"learn":[0.3631011739],"iteration":324,"passed_time":0.6929424531,"remaining_time":1.225975109},
{"learn":[0.3630062484],"iteration":325,"passed_time":0.6950749555,"remaining_time":1.223843633},
{"learn":[0.3629174193],"iteration":326,"passed_time":0.6972387971,"remaining_time":1.221767067},
{"learn":[0.3627946691],"iteration":327,"passed_time":0.699443525,"remaining_time":1.219761269},
{"learn":[0.3625677903],"iteration":328,"passed_time":0.7018525191,"remaining_time":1.218108779},
{"learn":[0.3624196935],"iteration":329,"passed_time":0.7042428169,"remaining_time":1.216419411},
{"learn":[0.3623303497],"iteration":330,"passed_time":0.7065677125,"remaining_time":1.214613379},
{"learn":[0.3622309687],"iteration":331,"passed_time":0.7086791427,"remaining_time":1.212439015},
{"learn":[0.3618776572],"iteration":332,"passed_time":0.7110831668,"remaining_time":1.21076323},
{"learn":[0.361703202],"iteration":333,"passed_time":0.7134190333,"remaining_time":1.208967583},
{"learn":[0.3614714791],"iteration":334,"passed_time":0.7157856104,"remaining_time":1.207220507},
{"learn":[0.3613678381],"iteration":335,"passed_time":0.7178424825,"remaining_time":1.204949881},
{"learn":[0.3610088639],"iteration":336,"passed_time":0.720006874,"remaining_time":1.202860148},
{"learn":[0.3608773395],"iteration":337,"passed_time":0.7221248304,"remaining_time":1.200692765},
{"learn":[0.3607415237],"iteration":338,"passed_time":0.7241756174,"remaining_time":1.198414517},
{"learn":[0.3606046282],"iteration":339,"passed_time":0.7263474046,"remaining_time":1.196336902},
{"learn":[0.3604916308],"iteration":340,"passed_time":0.7283776621,"remaining_time":1.194026725},
{"learn":[0.360386922],"iteration":341,"passed_time":0.7307282403,"remaining_time":1.192240813},
{"learn":[0.3603273959],"iteration":342,"passed_time":0.7328135477,"remaining_time":1.190020834},
{"learn":[0.3599725672],"iteration":343,"passed_time":0.7350003483,"remaining_time":1.187965679},
{"learn":[0.3598180973],"iteration":344,"passed_time":0.7372306329,"remaining_time":1.185979714},
{"learn":[0.3596093614],"iteration":345,"passed_time":0.7393868379,"remaining_time":1.183873723},
{"learn":[0.3595050653],"iteration":346,"passed_time":0.7415867533,"remaining_time":1.181837103},
{"learn":[0.3594364634],"iteration":347,"passed_time":0.7436648172,"remaining_time":1.179606262},
{"learn":[0.3593581818],"iteration":348,"passed_time":0.7458171789,"remaining_time":1.177493598},
{"learn":[0.3592842597],"iteration":349,"passed_time":0.7479377666,"remaining_time":1.175330776},
{"learn":[0.3590879851],"iteration":350,"passed_time":0.7499825683,"remaining_time":1.173049658},
{"learn":[0.3589736476],"iteration":351,"passed_time":0.7522516956,"remaining_time":1.171119117},
{"learn":[0.3587259291],"iteration":352,"passed_time":0.7543208629,"remaining_time":1.168876804},
{"learn":[0.3586152631],"iteration":353,"passed_time":0.7564157,"remaining_time":1.166675063},
{"learn":[0.3585929171],"iteration":354,"passed_time":0.7585033833,"remaining_time":1.164462941},
{"learn":[0.3584709718],"iteration":355,"passed_time":0.7606229303,"remaining_time":1.162300208},
{"learn":[0.3584361427],"iteration":356,"passed_time":0.7627926315,"remaining_time":1.160214003},
{"learn":[0.3583844213],"iteration":357,"passed_time":0.7651733533,"remaining_time":1.158446809},
{"learn":[0.3583410963],"iteration":358,"passed_time":0.7673396786,"remaining_time":1.156353109},
{"learn":[0.3580993945],"iteration":359,"passed_time":0.7693866849,"remaining_time":1.154080027},
{"learn":[0.3580413779],"iteration":360,"passed_time":0.7713696858,"remaining_time":1.151712633},
{"learn":[0.3577312404],"iteration":361,"passed_time":0.7733798547,"remaining_time":1.14938774},
{"learn":[0.3576406835],"iteration":362,"passed_time":0.7754842244,"remaining_time":1.147203935},
{"learn":[0.3576103845],"iteration":363,"passed_time":0.7773692909,"remaining_time":1.144697637},
{"learn":[0.3573768919],"iteration":364,"passed_time":0.7792990778,"remaining_time":1.142260292},
{"learn":[0.3572824023],"iteration":365,"passed_time":0.78142615,"remaining_time":1.140113563},
{"learn":[0.3572361452],"iteration":366,"passed_time":0.783440068,"remaining_time":1.137802606},
{"learn":[0.3568954923],"iteration":367,"passed_time":0.7855467619,"remaining_time":1.135627384},
{"learn":[0.356808781],"iteration":368,"passed_time":0.7877073437,"remaining_time":1.13353008},
{"learn":[0.356718921],"iteration":369,"passed_time":0.7897892499,"remaining_time":1.131319736},
{"learn":[0.3565634818],"iteration":370,"passed_time":0.7920066488,"remaining_time":1.129303281},
{"learn":[0.3563590928],"iteration":371,"passed_time":0.7939404909,"remaining_time":1.126883277},
{"learn":[0.3563043615],"iteration":372,"passed_time":0.7959519768,"remaining_time":1.124575581},
{"learn":[0.3559432035],"iteration":373,"passed_time":0.7980367661,"remaining_time":1.122372564},
{"learn":[0.3558414806],"iteration":374,"passed_time":0.8000472639,"remaining_time":1.120066169},
{"learn":[0.3555445185],"iteration":375,"passed_time":0.8020768347,"remaining_time":1.117787929},
{"learn":[0.3554686375],"iteration":376,"passed_time":0.8041267387,"remaining_time":1.115539216},
{"learn":[0.3552868546],"iteration":377,"passed_time":0.8061700403,"remaining_time":1.113282437},
{"learn":[0.3551251137],"iteration":378,"passed_time":0.8082057787,"remaining_time":1.111016387},
{"learn":[0.3550078131],"iteration":379,"passed_time":0.810234162,"remaining_time":1.108741485},
{"learn":[0.3548373531],"iteration":380,"passed_time":0.8122279499,"remaining_time":1.106420751},
{"learn":[0.3546725969],"iteration":381,"passed_time":0.8143740816,"remaining_time":1.10430831},
{"learn":[0.3545087373],"iteration":382,"passed_time":0.816465331,"remaining_time":1.102121609},
{"learn":[0.3543846983],"iteration":383,"passed_time":0.8184837553,"remaining_time":1.099837546},
{"learn":[0.3540944272],"iteration":384,"passed_time":0.8205236376,"remaining_time":1.097583567},
{"learn":[0.3540671096],"iteration":385,"passed_time":0.8225558896,"remaining_time":1.095320537},
{"learn":[0.3538366138],"iteration":386,"passed_time":0.8246218712,"remaining_time":1.093103411},
{"learn":[0.3535683386],"iteration":387,"passed_time":0.826675804,"remaining_time":1.090871164},
{"learn":[0.3534056015],"iteration":388,"passed_time":0.8286390741,"remaining_time":1.088520737},
{"learn":[0.353311559],"iteration":389,"passed_time":0.8306684457,"remaining_time":1.086258737},
{"learn":[0.3531609853],"iteration":390,"passed_time":0.8327694676,"remaining_time":1.0840912},
{"learn":[0.3530535778],"iteration":391,"passed_time":0.8348792421,"remaining_time":1.081935344},
{"learn":[0.3529192661],"iteration":392,"passed_time":0.8368040598,"remaining_time":1.079541115},
{"learn":[0.3528407198],"iteration":393,"passed_time":0.8389591833,"remaining_time":1.077445043},
{"learn":[0.3526776597],"iteration":394,"passed_time":0.8410113245,"remaining_time":1.07521701},
{"learn":[0.3525420579],"iteration":395,"passed_time":0.8429123356,"remaining_time":1.072797518},
{"learn":[0.3523820082],"iteration":396,"passed_time":0.844938305,"remaining_time":1.070538961},
{"learn":[0.3523605872],"iteration":397,"passed_time":0.8469500591,"remaining_time":1.068263642},
{"learn":[0.3523475857],"iteration":398,"passed_time":0.8489592136,"remaining_time":1.065986381},
{"learn":[0.3522425914],"iteration":399,"passed_time":0.8509252617,"remaining_time":1.063656577},
{"learn":[0.3519815932],"iteration":400,"passed_time":0.8528250092,"remaining_time":1.061246084},
{"learn":[0.3517001056],"iteration":401,"passed_time":0.8548449144,"remaining_time":1.058986984},
{"learn":[0.3516806074],"iteration":402,"passed_time":0.8569145708,"remaining_time":1.056790426},
{"learn":[0.3516591837],"iteration":403,"passed_time":0.8589500492,"remaining_time":1.054552536},
{"learn":[0.351471672],"iteration":404,"passed_time":0.8617747069,"remaining_time":1.053280197},
{"learn":[0.3512172829],"iteration":405,"passed_time":0.8638650424,"remaining_time":1.051106726},
{"learn":[0.3510436025],"iteration":406,"passed_time":0.8659568868,"remaining_time":1.048935492},
{"learn":[0.3509690563],"iteration":407,"passed_time":0.8680915713,"remaining_time":1.046816307},
{"learn":[0.3508592568],"iteration":408,"passed_time":0.8701581027,"remaining_time":1.044615228},
{"learn":[0.3506201382],"iteration":409,"passed_time":0.8723762316,"remaining_time":1.042595984},
{"learn":[0.3506174093],"iteration":410,"passed_time":0.8743530985,"remaining_time":1.040288723},
{"learn":[0.350405251],"iteration":411,"passed_time":0.8765580719,"remaining_time":1.03825325},
{"learn":[0.3503551131],"iteration":412,"passed_time":0.8785008097,"remaining_time":1.035907734},
{"learn":[0.3501201583],"iteration":413,"passed_time":0.8808880885,"remaining_time":1.034086017},
{"learn":[0.3499796583],"iteration":414,"passed_time":0.8831037193,"remaining_time":1.032060973},
{"learn":[0.349959117],"iteration":415,"passed_time":0.8850561916,"remaining_time":1.029728838},
{"learn":[0.3496567636],"iteration":416,"passed_time":0.8872703804,"remaining_time":1.027701664},
{"learn":[0.3494865399],"iteration":417,"passed_time":0.889240924,"remaining_time":1.025392644},
{"learn":[0.3493716691],"iteration":418,"passed_time":0.891247573,"remaining_time":1.023126689},
{"learn":[0.3492374279],"iteration":419,"passed_time":0.8934344977,"remaining_time":1.021067997},
{"learn":[0.3492038974],"iteration":420,"passed_time":0.8953671967,"remaining_time":1.018719447},
{"learn":[0.3490430446],"iteration":421,"passed_time":0.8974801849,"remaining_time":1.016577081},
{"learn":[0.3487348915],"iteration":422,"passed_time":0.8994720516,"remaining_time":1.014298271},
{"learn":[0.34857742],"iteration":423,"passed_time":0.9016304984,"remaining_time":1.012207824},
{"learn":[0.3485011997],"iteration":424,"passed_time":0.9037400437,"remaining_time":1.010062402},
{"learn":[0.3483074868],"iteration":425,"passed_time":0.9056940658,"remaining_time":1.007744101},
{"learn":[0.3481904849],"iteration":426,"passed_time":0.9078413442,"remaining_time":1.005641583},
{"learn":[0.3480223634],"iteration":427,"passed_time":0.9099812306,"remaining_time":1.003530703},
{"learn":[0.3478839729],"iteration":428,"passed_time":0.9120149346,"remaining_time":1.00130311},
{"learn":[0.3478112322],"iteration":429,"passed_time":0.914468275,"remaining_time":0.9995350913},
{"learn":[0.3476787555],"iteration":430,"passed_time":0.9165931036,"remaining_time":0.9974064167},
{"learn":[0.3475855764],"iteration":431,"passed_time":0.9187353079,"remaining_time":0.9952965835},
{"learn":[0.347378515],"iteration":432,"passed_time":0.9210025258,"remaining_time":0.9933214309},
{"learn":[0.3472242584],"iteration":433,"passed_time":0.9234971166,"remaining_time":0.9915890699},
{"learn":[0.347052855],"iteration":434,"passed_time":0.9257733009,"remaining_time":0.9896197354},
{"learn":[0.346933709],"iteration":435,"passed_time":0.927826385,"remaining_time":0.9874115657},
{"learn":[0.3468740919],"iteration":436,"passed_time":0.9299865048,"remaining_time":0.9853175097},
{"learn":[0.3466595654],"iteration":437,"passed_time":0.9319544986,"remaining_time":0.9830204985},
{"learn":[0.3464499959],"iteration":438,"passed_time":0.9340761543,"remaining_time":0.9808863488},
{"learn":[0.3463915832],"iteration":439,"passed_time":0.9363441575,"remaining_time":0.9789052556},
{"learn":[0.3463051631],"iteration":440,"passed_time":0.9385269102,"remaining_time":0.976834131},
{"learn":[0.346204902],"iteration":441,"passed_time":0.9405749817,"remaining_time":0.9746229448},
{"learn":[0.3461009166],"iteration":442,"passed_time":0.9426170714,"remaining_time":0.9724063242},
{"learn":[0.345843601],"iteration":443,"passed_time":0.9447704594,"remaining_time":0.9703047961},
{"learn":[0.3458311669],"iteration":444,"passed_time":0.9468872039,"remaining_time":0.968165568},
{"learn":[0.3458133541],"iteration":445,"passed_time":0.9491711444,"remaining_time":0.9661966358},
{"learn":[0.3455885725],"iteration":446,"passed_time":0.9512569002,"remaining_time":0.9640254492},
{"learn":[0.3454599779],"iteration":447,"passed_time":0.9533766057,"remaining_time":0.9618888968},
{"learn":[0.345369016],"iteration":448,"passed_time":0.9555753672,"remaining_time":0.9598318276},
{"learn":[0.3452839587],"iteration":449,"passed_time":0.9578725657,"remaining_time":0.9578725657},
{"learn":[0.3450386869],"iteration":450,"passed_time":0.9601574582,"remaining_time":0.9558995537},
{"learn":[0.3449104178],"iteration":451,"passed_time":0.9621741497,"remaining_time":0.9536593342},
{"learn":[0.3446506071],"iteration":452,"passed_time":0.964392026,"remaining_time":0.9516186217},
{"learn":[0.3444820221],"iteration":453,"passed_time":0.9663650578,"remaining_time":0.9493365986},
{"learn":[0.3442554089],"iteration":454,"passed_time":0.9684774898,"remaining_time":0.9471922702},
{"learn":[0.3442413674],"iteration":455,"passed_time":0.9704141226,"remaining_time":0.9448769089},
{"learn":[0.3440546459],"iteration":456,"passed_time":0.9723976588,"remaining_time":0.9426086714},
{"learn":[0.3440112702],"iteration":457,"passed_time":0.9744899244,"remaining_time":0.9404466083},
{"learn":[0.3438631047],"iteration":458,"passed_time":0.9764988126,"remaining_time":0.9382047415},
{"learn":[0.3438150384],"iteration":459,"passed_time":0.9783450608,"remaining_time":0.935808319},
{"learn":[0.343689348],"iteration":460,"passed_time":0.9802372042,"remaining_time":0.9334579884},
{"learn":[0.3435588608],"iteration":461,"passed_time":0.9822071599,"remaining_time":0.9311834114},
{"learn":[0.3435038583],"iteration":462,"passed_time":0.9841433942,"remaining_time":0.9288783224},
{"learn":[0.3434606976],"iteration":463,"passed_time":0.9860970612,"remaining_time":0.9265912041},
{"learn":[0.3434114327],"iteration":464,"passed_time":0.9879339735,"remaining_time":0.9241962978},
{"learn":[0.3433554292],"iteration":465,"passed_time":0.9898445795,"remaining_time":0.9218724195},
{"learn":[0.3431636495],"iteration":466,"passed_time":0.9917185076,"remaining_time":0.9195163036},
{"learn":[0.3429036995],"iteration":467,"passed_time":0.9935484815,"remaining_time":0.9171216753},
{"learn":[0.3426444588],"iteration":468,"passed_time":0.9954065412,"remaining_time":0.9147552649},
{"learn":[0.3426292568],"iteration":469,"passed_time":0.9973196779,"remaining_time":0.9124414075},
{"learn":[0.3425385849],"iteration":470,"passed_time":0.9992269144,"remaining_time":0.9101238775},
{"learn":[0.3424346684],"iteration":471,"passed_time":1.00099349,"remaining_time":0.9076805374},
{"learn":[0.3424331041],"iteration":472,"passed_time":1.00294487,"remaining_time":0.9054068908},
{"learn":[0.342372294],"iteration":473,"passed_time":1.004878938,"remaining_time":0.9031190458},
{"learn":[0.3422565073],"iteration":474,"passed_time":1.006922322,"remaining_time":0.9009304989},
{"learn":[0.3421698972],"iteration":475,"passed_time":1.008875109,"remaining_time":0.8986618617},
{"learn":[0.3420026457],"iteration":476,"passed_time":1.010904946,"remaining_time":0.8964628767},
{"learn":[0.341875191],"iteration":477,"passed_time":1.012871672,"remaining_time":0.8942088818},
{"learn":[0.3416322947],"iteration":478,"passed_time":1.014834119,"remaining_time":0.8919523263},
{"learn":[0.3414672819],"iteration":479,"passed_time":1.016790986,"remaining_time":0.8896921125},
{"learn":[0.3414145284],"iteration":480,"passed_time":1.018743953,"remaining_time":0.887429764},
{"learn":[0.3412706453],"iteration":481,"passed_time":1.020826732,"remaining_time":0.8852812738},
{"learn":[0.3411880396],"iteration":482,"passed_time":1.022864937,"remaining_time":0.8830945727},
{"learn":[0.3409459914],"iteration":483,"passed_time":1.024804803,"remaining_time":0.8808239631},
{"learn":[0.3408597367],"iteration":484,"passed_time":1.026883523,"remaining_time":0.8786735299},
{"learn":[0.3408364749],"iteration":485,"passed_time":1.029050662,"remaining_time":0.8765987125},
{"learn":[0.3406270776],"iteration":486,"passed_time":1.031188894,"remaining_time":0.8744990004},
{"learn":[0.3405095571],"iteration":487,"passed_time":1.033842378,"remaining_time":0.8728341391},
{"learn":[0.3404371888],"iteration":488,"passed_time":1.036046531,"remaining_time":0.8707875752},
{"learn":[0.3402852965],"iteration":489,"passed_time":1.038362579,"remaining_time":0.8688339947},
{"learn":[0.3402692066],"iteration":490,"passed_time":1.040463173,"remaining_time":0.8666994662},
{"learn":[0.3400933427],"iteration":491,"passed_time":1.042412419,"remaining_time":0.8644395671},
{"learn":[0.3399896242],"iteration":492,"passed_time":1.044501959,"remaining_time":0.8622967494},
{"learn":[0.3399885812],"iteration":493,"passed_time":1.046196325,"remaining_time":0.859829368},
{"learn":[0.3398882395],"iteration":494,"passed_time":1.048152124,"remaining_time":0.8575790105},
{"learn":[0.3396891967],"iteration":495,"passed_time":1.050090978,"remaining_time":0.8553160383},
{"learn":[0.3393769482],"iteration":496,"passed_time":1.05221061,"remaining_time":0.8532009573},
{"learn":[0.3391978895],"iteration":497,"passed_time":1.054241865,"remaining_time":0.8510145172},
{"learn":[0.3390229478],"iteration":498,"passed_time":1.056267505,"remaining_time":0.8488241875},
{"learn":[0.3389024541],"iteration":499,"passed_time":1.058385165,"remaining_time":0.8467081323},
{"learn":[0.3387852115],"iteration":500,"passed_time":1.060372509,"remaining_time":0.8444882853},
{"learn":[0.3386715897],"iteration":501,"passed_time":1.062454488,"remaining_time":0.842344395},
{"learn":[0.3385835907],"iteration":502,"passed_time":1.064438369,"remaining_time":0.8401233247},
{"learn":[0.3384988941],"iteration":503,"passed_time":1.066537311,"remaining_time":0.8379936013},
{"learn":[0.3384925557],"iteration":504,"passed_time":1.068516628,"remaining_time":0.8357704316},
{"learn":[0.3384263059],"iteration":505,"passed_time":1.070527894,"remaining_time":0.8335731036},
{"learn":[0.3381890482],"iteration":506,"passed_time":1.072542711,"remaining_time":0.8313792612},
{"learn":[0.3379841407],"iteration":507,"passed_time":1.074488273,"remaining_time":0.8291326832},
{"learn":[0.3379161338],"iteration":508,"passed_time":1.076494138,"remaining_time":0.8269336107},
{"learn":[0.3377954741],"iteration":509,"passed_time":1.0785217,"remaining_time":0.8247518879},
{"learn":[0.3377848027],"iteration":510,"passed_time":1.080443679,"remaining_time":0.8224903933},
{"learn":[0.3376771858],"iteration":511,"passed_time":1.082394911,"remaining_time":0.8202523934},
{"learn":[0.3375672766],"iteration":512,"passed_time":1.084387296,"remaining_time":0.8180465564},
{"learn":[0.3373948964],"iteration":513,"passed_time":1.086396921,"remaining_time":0.8158544972},
{"learn":[0.3373204288],"iteration":514,"passed_time":1.088410484,"remaining_time":0.81366609},
{"learn":[0.3371840173],"iteration":515,"passed_time":1.090437579,"remaining_time":0.8114884312},
{"learn":[0.3371668469],"iteration":516,"passed_time":1.09246751,"remaining_time":0.8093134551},
{"learn":[0.3371582218],"iteration":517,"passed_time":1.094418724,"remaining_time":0.8070809895},
{"learn":[0.3370631163],"iteration":518,"passed_time":1.096279763,"remaining_time":0.8047834097},
{"learn":[0.3368195254],"iteration":519,"passed_time":1.098200181,"remaining_time":0.8025309016},
{"learn":[0.3367644778],"iteration":520,"passed_time":1.100182339,"remaining_time":0.8003245804},
{"learn":[0.3365813194],"iteration":521,"passed_time":1.102116809,"remaining_time":0.7980845855},
{"learn":[0.3365793943],"iteration":522,"passed_time":1.103947373,"remaining_time":0.7957708597},
{"learn":[0.3365629021],"iteration":523,"passed_time":1.105921417,"remaining_time":0.7935619332},
{"learn":[0.3364904242],"iteration":524,"passed_time":1.107940922,"remaining_time":0.7913863731},
{"learn":[0.3363973375],"iteration":525,"passed_time":1.10981875,"remaining_time":0.78911067},
{"learn":[0.3361563047],"iteration":526,"passed_time":1.111686122,"remaining_time":0.7868290768},
{"learn":[0.3360348882],"iteration":527,"passed_time":1.11351848,"remaining_time":0.7845243835},
{"learn":[0.3359285109],"iteration":528,"passed_time":1.115360416,"remaining_time":0.7822281938},
{"learn":[0.335731578],"iteration":529,"passed_time":1.117236316,"remaining_time":0.7799574278},
{"learn":[0.3355819809],"iteration":530,"passed_time":1.119013135,"remaining_time":0.7776192975},
{"learn":[0.3353447103],"iteration":531,"passed_time":1.120907046,"remaining_time":0.7753642724},
{"learn":[0.335296869],"iteration":532,"passed_time":1.122720326,"remaining_time":0.773055084},
{"learn":[0.3352644324],"iteration":533,"passed_time":1.124638627,"remaining_time":0.7708197331},
{"learn":[0.3350711719],"iteration":534,"passed_time":1.126480126,"remaining_time":0.7685331701},
{"learn":[0.3350523482],"iteration":535,"passed_time":1.128297801,"remaining_time":0.766232089},
{"learn":[0.3348732927],"iteration":536,"passed_time":1.130171474,"remaining_time":0.7639706612},
{"learn":[0.3347100312],"iteration":537,"passed_time":1.132097491,"remaining_time":0.7617458954},
{"learn":[0.3346005079],"iteration":538,"passed_time":1.134011257,"remaining_time":0.7595140332},
{"learn":[0.3345380138],"iteration":539,"passed_time":1.135844286,"remaining_time":0.7572295243},
{"learn":[0.33448977],"iteration":540,"passed_time":1.137782517,"remaining_time":0.7550164947},
{"learn":[0.3343997686],"iteration":541,"passed_time":1.139571132,"remaining_time":0.7527056555},
{"learn":[0.3342702373],"iteration":542,"passed_time":1.141473225,"remaining_time":0.7504713465},
{"learn":[0.3340432409],"iteration":543,"passed_time":1.143333662,"remaining_time":0.7482109993},
{"learn":[0.3338316612],"iteration":544,"passed_time":1.145169835,"remaining_time":0.7459363146},
{"learn":[0.3338303574],"iteration":545,"passed_time":1.147047221,"remaining_time":0.7436899567},
{"learn":[0.3337681002],"iteration":546,"passed_time":1.148904569,"remaining_time":0.7414320162},
{"learn":[0.3337212807],"iteration":547,"passed_time":1.150791918,"remaining_time":0.7391948087},
{"learn":[0.3335689822],"iteration":548,"passed_time":1.15266329,"remaining_time":0.7369486609},
{"learn":[0.3334021642],"iteration":549,"passed_time":1.154601606,"remaining_time":0.7347464765},
{"learn":[0.3333901271],"iteration":550,"passed_time":1.156517182,"remaining_time":0.7325308466},
{"learn":[0.3333313745],"iteration":551,"passed_time":1.158403761,"remaining_time":0.7302980233},
{"learn":[0.3331864313],"iteration":552,"passed_time":1.160279236,"remaining_time":0.7280594846},
{"learn":[0.33318246],"iteration":553,"passed_time":1.162079996,"remaining_time":0.7257755931},
{"learn":[0.3330777106],"iteration":554,"passed_time":1.163870942,"remaining_time":0.7234873425},
{"learn":[0.332973614],"iteration":555,"passed_time":1.165727052,"remaining_time":0.7212411975},
{"learn":[0.3329338647],"iteration":556,"passed_time":1.167577332,"remaining_time":0.7189928631},
{"learn":[0.3327996747],"iteration":557,"passed_time":1.16945352,"remaining_time":0.7167618346},
{"learn":[0.3327540515],"iteration":558,"passed_time":1.17118593,"remaining_time":0.7144443686},
{"learn":[0.3326299363],"iteration":559,"passed_time":1.172995473,"remaining_time":0.7121758228},
{"learn":[0.3326182859],"iteration":560,"passed_time":1.174852407,"remaining_time":0.709937551},
{"learn":[0.3326176046],"iteration":561,"passed_time":1.176688438,"remaining_time":0.7076880638},
{"learn":[0.3324778142],"iteration":562,"passed_time":1.1785901,"remaining_time":0.7054793315},
{"learn":[0.3324655537],"iteration":563,"passed_time":1.180428487,"remaining_time":0.7032339921},
{"learn":[0.3322834191],"iteration":564,"passed_time":1.182406089,"remaining_time":0.7010726369},
{"learn":[0.3321235232],"iteration":565,"passed_time":1.184387633,"remaining_time":0.6989142572},
{"learn":[0.3319694235],"iteration":566,"passed_time":1.186274317,"remaining_time":0.6967007892},
{"learn":[0.3319349234],"iteration":567,"passed_time":1.188200086,"remaining_time":0.6945113176},
{"learn":[0.3318547673],"iteration":568,"passed_time":1.190043464,"remaining_time":0.6922748448},
{"learn":[0.3317490749],"iteration":569,"passed_time":1.191943751,"remaining_time":0.6900726977},
{"learn":[0.3316283591],"iteration":570,"passed_time":1.193759439,"remaining_time":0.6878228639},
{"learn":[0.3315960395],"iteration":571,"passed_time":1.19561895,"remaining_time":0.6855996777},
{"learn":[0.3315293175],"iteration":572,"passed_time":1.197511298,"remaining_time":0.6833965001},
{"learn":[0.3314346502],"iteration":573,"passed_time":1.199322878,"remaining_time":0.6811485333},
{"learn":[0.3314004281],"iteration":574,"passed_time":1.201161178,"remaining_time":0.6789171878},
{"learn":[0.3312418068],"iteration":575,"passed_time":1.203062681,"remaining_time":0.6767227582},
{"learn":[0.3311251316],"iteration":576,"passed_time":1.204922226,"remaining_time":0.6745058564},
{"learn":[0.3311068991],"iteration":577,"passed_time":1.206753876,"remaining_time":0.6722746507},
{"learn":[0.3309421746],"iteration":578,"passed_time":1.208600392,"remaining_time":0.6700530673},
{"learn":[0.3308375879],"iteration":579,"passed_time":1.210499122,"remaining_time":0.6678615844},
{"learn":[0.3306063622],"iteration":580,"passed_time":1.212345987,"remaining_time":0.665642633},
{"learn":[0.3305357669],"iteration":581,"passed_time":1.21430132,"remaining_time":0.6634842266},
{"learn":[0.3305105847],"iteration":582,"passed_time":1.216132515,"remaining_time":0.6612590178},
{"learn":[0.3303544369],"iteration":583,"passed_time":1.218075018,"remaining_time":0.6590953863},
{"learn":[0.3302357559],"iteration":584,"passed_time":1.21990454,"remaining_time":0.6568716752},
{"learn":[0.330181106],"iteration":585,"passed_time":1.221672975,"remaining_time":0.6546165768},
{"learn":[0.3300445318],"iteration":586,"passed_time":1.223492079,"remaining_time":0.6523901547},
{"learn":[0.3299523566],"iteration":587,"passed_time":1.225396971,"remaining_time":0.6502106375},
{"learn":[0.3298844036],"iteration":588,"passed_time":1.227149881,"remaining_time":0.6479518049},
{"learn":[0.3298246305],"iteration":589,"passed_time":1.229027372,"remaining_time":0.6457601445},
{"learn":[0.3297761162],"iteration":590,"passed_time":1.230966489,"remaining_time":0.6436017685},
{"learn":[0.3297399258],"iteration":591,"passed_time":1.232866736,"remaining_time":0.6414239098},
{"learn":[0.3296433612],"iteration":592,"passed_time":1.234853285,"remaining_time":0.6392916667},
{"learn":[0.3295841804],"iteration":593,"passed_time":1.237057458,"remaining_time":0.6372720239},
{"learn":[0.3295777215],"iteration":594,"passed_time":1.239222537,"remaining_time":0.6352317207},
{"learn":[0.3295632934],"iteration":595,"passed_time":1.241348184,"remaining_time":0.6331708861},
{"learn":[0.3294874883],"iteration":596,"passed_time":1.243277236,"remaining_time":0.6310100544},
{"learn":[0.3294778211],"iteration":597,"passed_time":1.24509783,"remaining_time":0.628795225},
{"learn":[0.3294626554],"iteration":598,"passed_time":1.246964394,"remaining_time":0.6266048121},
{"learn":[0.3294614695],"iteration":599,"passed_time":1.248819415,"remaining_time":0.6244097076},
{"learn":[0.3292703733],"iteration":600,"passed_time":1.250719648,"remaining_time":0.6222382276},
{"learn":[0.3292691255],"iteration":601,"passed_time":1.25267561,"remaining_time":0.6200952357},
{"learn":[0.3291191916],"iteration":602,"passed_time":1.254662671,"remaining_time":0.6179681813},
{"learn":[0.3289279559],"iteration":603,"passed_time":1.256596005,"remaining_time":0.6158152607},
{"learn":[0.3288639978],"iteration":604,"passed_time":1.258526934,"remaining_time":0.6136618935},
{"learn":[0.3287425661],"iteration":605,"passed_time":1.260477707,"remaining_time":0.6115188876},
{"learn":[0.3285681079],"iteration":606,"passed_time":1.262333259,"remaining_time":0.6093305515},
{"learn":[0.3284201651],"iteration":607,"passed_time":1.264799124,"remaining_time":0.6074364215},
{"learn":[0.3283330982],"iteration":608,"passed_time":1.266947914,"remaining_time":0.6053889045},
{"learn":[0.3282735778],"iteration":609,"passed_time":1.269134368,"remaining_time":0.6033589619},
{"learn":[0.3281903277],"iteration":610,"passed_time":1.271248268,"remaining_time":0.6012941892},
{"learn":[0.3281897466],"iteration":611,"passed_time":1.27251707,"remaining_time":0.5988315623},
{"learn":[0.3281287631],"iteration":612,"passed_time":1.274510296,"remaining_time":0.5967119983},
{"learn":[0.3280672537],"iteration":613,"passed_time":1.276418987,"remaining_time":0.5945534697},
{"learn":[0.3279893006],"iteration":614,"passed_time":1.278234567,"remaining_time":0.592352604},
{"learn":[0.3279146761],"iteration":615,"passed_time":1.280083003,"remaining_time":0.5901681378},
{"learn":[0.3276854819],"iteration":616,"passed_time":1.281905452,"remaining_time":0.5879728409},
{"learn":[0.327600187],"iteration":617,"passed_time":1.283747458,"remaining_time":0.5857876751},
{"learn":[0.3275177143],"iteration":618,"passed_time":1.285597149,"remaining_time":0.5836071065},
{"learn":[0.327465631],"iteration":619,"passed_time":1.287491991,"remaining_time":0.5814479959},
{"learn":[0.3274341446],"iteration":620,"passed_time":1.289431953,"remaining_time":0.5793100077},
{"learn":[0.3273801455],"iteration":621,"passed_time":1.291262975,"remaining_time":0.5771239665},
{"learn":[0.3272924108],"iteration":622,"passed_time":1.293227873,"remaining_time":0.5749985889},
{"learn":[0.3272236444],"iteration":623,"passed_time":1.29512334,"remaining_time":0.5728430158},
{"learn":[0.3271695395],"iteration":624,"passed_time":1.296980141,"remaining_time":0.5706712619},
{"learn":[0.3270460964],"iteration":625,"passed_time":1.298842326,"remaining_time":0.5685028712},
{"learn":[0.3268331083],"iteration":626,"passed_time":1.300722083,"remaining_time":0.5663431079},
{"learn":[0.3267825264],"iteration":627,"passed_time":1.302639313,"remaining_time":0.5642004667},
{"learn":[0.3267709327],"iteration":628,"passed_time":1.304493595,"remaining_time":0.5620314215},
{"learn":[0.3266885145],"iteration":629,"passed_time":1.306447053,"remaining_time":0.5599058799},
{"learn":[0.3266198525],"iteration":630,"passed_time":1.308340549,"remaining_time":0.5577553212},
{"learn":[0.3265555059],"iteration":631,"passed_time":1.310253625,"remaining_time":0.555613879},
{"learn":[0.3265064602],"iteration":632,"passed_time":1.312091319,"remaining_time":0.553441362},
{"learn":[0.3264489622],"iteration":633,"passed_time":1.313904459,"remaining_time":0.5512595995},
{"learn":[0.3263968654],"iteration":634,"passed_time":1.315765449,"remaining_time":0.5490989668},
{"learn":[0.3262870971],"iteration":635,"passed_time":1.317561882,"remaining_time":0.5469124791},
{"learn":[0.3261257528],"iteration":636,"passed_time":1.319541462,"remaining_time":0.5448028329},
{"learn":[0.3260083953],"iteration":637,"passed_time":1.321449928,"remaining_time":0.5426643904},
{"learn":[0.3258139315],"iteration":638,"passed_time":1.323977859,"remaining_time":0.5407796887},
{"learn":[0.3257406434],"iteration":639,"passed_time":1.326009334,"remaining_time":0.5386912921},
{"learn":[0.3257159233],"iteration":640,"passed_time":1.327858286,"remaining_time":0.5365293232},
{"learn":[0.3256155753],"iteration":641,"passed_time":1.329847927,"remaining_time":0.5344248677},
{"learn":[0.3255681093],"iteration":642,"passed_time":1.33184619,"remaining_time":0.5323242159},
{"learn":[0.3255369161],"iteration":643,"passed_time":1.333890655,"remaining_time":0.5302422481},
{"learn":[0.3254286569],"iteration":644,"passed_time":1.336016459,"remaining_time":0.5281925534},
{"learn":[0.3253421201],"iteration":645,"passed_time":1.338254466,"remaining_time":0.5261867405},
{"learn":[0.3252377053],"iteration":646,"passed_time":1.340216641,"remaining_time":0.5240723496},
{"learn":[0.3251929272],"iteration":647,"passed_time":1.342115222,"remaining_time":0.5219336974},
{"learn":[0.3250050703],"iteration":648,"passed_time":1.344059184,"remaining_time":0.5198133363},
{"learn":[0.324921101],"iteration":649,"passed_time":1.346124021,"remaining_time":0.5177400081},
{"learn":[0.3247643359],"iteration":650,"passed_time":1.348231167,"remaining_time":0.5156828887},
{"learn":[0.3245539408],"iteration":651,"passed_time":1.350298927,"remaining_time":0.513610635},
{"learn":[0.3244538817],"iteration":652,"passed_time":1.352428761,"remaining_time":0.5115618745},
{"learn":[0.3244509521],"iteration":653,"passed_time":1.354503799,"remaining_time":0.5094922547},
{"learn":[0.3243952606],"iteration":654,"passed_time":1.356559924,"remaining_time":0.507415544},
{"learn":[0.3242812587],"iteration":655,"passed_time":1.358759507,"remaining_time":0.5053922556},
{"learn":[0.3240839995],"iteration":656,"passed_time":1.36086155,"remaining_time":0.5033323543},
{"learn":[0.3240148254],"iteration":657,"passed_time":1.36288705,"remaining_time":0.5012441733},
{"learn":[0.3239663993],"iteration":658,"passed_time":1.364979243,"remaining_time":0.4991805729},
{"learn":[0.3238911113],"iteration":659,"passed_time":1.366919239,"remaining_time":0.4970615415},
{"learn":[0.3238906293],"iteration":660,"passed_time":1.368010913,"remaining_time":0.4946363212},
{"learn":[0.323888763],"iteration":661,"passed_time":1.369911254,"remaining_time":0.4925058587},
{"learn":[0.3237525831],"iteration":662,"passed_time":1.371860293,"remaining_time":0.4903934982},
{"learn":[0.3236163408],"iteration":663,"passed_time":1.373739613,"remaining_time":0.4882568503},
{"learn":[0.3235674534],"iteration":664,"passed_time":1.37567944,"remaining_time":0.4861423586},
{"learn":[0.3235666905],"iteration":665,"passed_time":1.377842748,"remaining_time":0.4841069113},
{"learn":[0.3235332654],"iteration":666,"passed_time":1.379809717,"remaining_time":0.4820024948},
{"learn":[0.3234802942],"iteration":667,"passed_time":1.381682757,"remaining_time":0.4798658678},
{"learn":[0.3234734334],"iteration":668,"passed_time":1.383463099,"remaining_time":0.4776980207},
{"learn":[0.3233543864],"iteration":669,"passed_time":1.385419112,"remaining_time":0.4755916354},
{"learn":[0.3232534264],"iteration":670,"passed_time":1.387283586,"remaining_time":0.4734544579},
{"learn":[0.3231129146],"iteration":671,"passed_time":1.389112728,"remaining_time":0.471306104},
{"learn":[0.3231079248],"iteration":672,"passed_time":1.390963845,"remaining_time":0.4691661113},
{"learn":[0.3230104579],"iteration":673,"passed_time":1.392851774,"remaining_time":0.4670393189},
{"learn":[0.3228685573],"iteration":674,"passed_time":1.394716322,"remaining_time":0.4649054407},
{"learn":[0.3228430625],"iteration":675,"passed_time":1.396668312,"remaining_time":0.4628013343},
{"learn":[0.3228170989],"iteration":676,"passed_time":1.398467319,"remaining_time":0.4606472854},
{"learn":[0.3226035943],"iteration":677,"passed_time":1.400478892,"remaining_time":0.4585638851},
{"learn":[0.322602952],"iteration":678,"passed_time":1.402296454,"remaining_time":0.4564175499},
{"learn":[0.3225380749],"iteration":679,"passed_time":1.404247072,"remaining_time":0.4543152293},
{"learn":[0.3225101501],"iteration":680,"passed_time":1.406157501,"remaining_time":0.4522004298},
{"learn":[0.3223143647],"iteration":681,"passed_time":1.408193714,"remaining_time":0.4501264364},
{"learn":[0.3222584921],"iteration":682,"passed_time":1.410115591,"remaining_time":0.4480162274},
{"learn":[0.3222025659],"iteration":683,"passed_time":1.412045516,"remaining_time":0.4459091103},
{"learn":[0.3219888752],"iteration":684,"passed_time":1.413903076,"remaining_time":0.4437797975},
{"learn":[0.3218849834],"iteration":685,"passed_time":1.415833016,"remaining_time":0.4416738562},
{"learn":[0.3218610886],"iteration":686,"passed_time":1.417681969,"remaining_time":0.439543318},
{"learn":[0.3218002849],"iteration":687,"passed_time":1.419544582,"remaining_time":0.4374178071},
{"learn":[0.3217994224],"iteration":688,"passed_time":1.420926315,"remaining_time":0.4351457947},
{"learn":[0.3217569547],"iteration":689,"passed_time":1.422860681,"remaining_time":0.4330445551},
{"learn":[0.3217034762],"iteration":690,"passed_time":1.424778228,"remaining_time":0.4309387115},
{"learn":[0.3216595562],"iteration":691,"passed_time":1.426660543,"remaining_time":0.4288228221},
{"learn":[0.3215762898],"iteration":692,"passed_time":1.428485499,"remaining_time":0.4266904736},
{"learn":[0.3215263224],"iteration":693,"passed_time":1.430517899,"remaining_time":0.4246205868},
{"learn":[0.3213782824],"iteration":694,"passed_time":1.432532378,"remaining_time":0.4225455215},
{"learn":[0.3213266373],"iteration":695,"passed_time":1.434530196,"remaining_time":0.4204657472},
{"learn":[0.3212213764],"iteration":696,"passed_time":1.436424157,"remaining_time":0.4183559596},
{"learn":[0.3211194252],"iteration":697,"passed_time":1.438397691,"remaining_time":0.416269819},
{"learn":[0.3210043444],"iteration":698,"passed_time":1.440247083,"remaining_time":0.414148303},
{"learn":[0.3209553195],"iteration":699,"passed_time":1.442100197,"remaining_time":0.4120286276},
{"learn":[0.3209035314],"iteration":700,"passed_time":1.443914523,"remaining_time":0.409898702},
{"learn":[0.3209014251],"iteration":701,"passed_time":1.445824225,"remaining_time":0.4077965763},
{"learn":[0.3208543316],"iteration":702,"passed_time":1.447751328,"remaining_time":0.4056998743},
{"learn":[0.3208385999],"iteration":703,"passed_time":1.449656633,"remaining_time":0.4035975852},
{"learn":[0.3207613276],"iteration":704,"passed_time":1.451622978,"remaining_time":0.4015127386},
{"learn":[0.3207114968],"iteration":705,"passed_time":1.453475357,"remaining_time":0.399396911},
{"learn":[0.3205171679],"iteration":706,"passed_time":1.455478986,"remaining_time":0.3973231177},
{"learn":[0.3204672979],"iteration":707,"passed_time":1.457493256,"remaining_time":0.3952524084},
{"learn":[0.3203706938],"iteration":708,"passed_time":1.459641597,"remaining_time":0.3932179761},
{"learn":[0.3202579516],"iteration":709,"passed_time":1.461534748,"remaining_time":0.3911149325},
{"learn":[0.3202563053],"iteration":710,"passed_time":1.463429632,"remaining_time":0.3890129401},
{"learn":[0.3202113209],"iteration":711,"passed_time":1.465356229,"remaining_time":0.3869199031},
{"learn":[0.3201153378],"iteration":712,"passed_time":1.46723645,"remaining_time":0.38481517},
{"learn":[0.3200621036],"iteration":713,"passed_time":1.469111231,"remaining_time":0.3827096483},
{"learn":[0.3200194876],"iteration":714,"passed_time":1.470957573,"remaining_time":0.380597414},
{"learn":[0.3199785836],"iteration":715,"passed_time":1.472790644,"remaining_time":0.3784825118},
{"learn":[0.3199333087],"iteration":716,"passed_time":1.474763986,"remaining_time":0.3764041973},
{"learn":[0.3199049392],"iteration":717,"passed_time":1.476485801,"remaining_time":0.3742624176},
{"learn":[0.3197221448],"iteration":718,"passed_time":1.478272906,"remaining_time":0.3721382421},
{"learn":[0.3196459927],"iteration":719,"passed_time":1.48010358,"remaining_time":0.3700258949},
{"learn":[0.3196169452],"iteration":720,"passed_time":1.481886648,"remaining_time":0.3679025105},
{"learn":[0.3194623256],"iteration":721,"passed_time":1.483720421,"remaining_time":0.3657925692},
{"learn":[0.3192613104],"iteration":722,"passed_time":1.485531618,"remaining_time":0.3636778651},
{"learn":[0.3191559916],"iteration":723,"passed_time":1.487324932,"remaining_time":0.3615596519},
{"learn":[0.3190418917],"iteration":724,"passed_time":1.489238998,"remaining_time":0.3594714822},
{"learn":[0.3188665059],"iteration":725,"passed_time":1.491103636,"remaining_time":0.3573719458},
{"learn":[0.3188605479],"iteration":726,"passed_time":1.492921559,"remaining_time":0.3552619392},
{"learn":[0.3188407667],"iteration":727,"passed_time":1.494698828,"remaining_time":0.3531431296},
{"learn":[0.3186619584],"iteration":728,"passed_time":1.496513872,"remaining_time":0.3510341182},
{"learn":[0.3186088698],"iteration":729,"passed_time":1.498327707,"remaining_time":0.3489256304},
{"learn":[0.3185381369],"iteration":730,"passed_time":1.500257014,"remaining_time":0.3468446448},
{"learn":[0.3184308912],"iteration":731,"passed_time":1.502091855,"remaining_time":0.3447423929},
{"learn":[0.3183982317],"iteration":732,"passed_time":1.504000647,"remaining_time":0.3426577191},
{"learn":[0.3183427052],"iteration":733,"passed_time":1.505875704,"remaining_time":0.3405658949},
{"learn":[0.3181504272],"iteration":734,"passed_time":1.507697712,"remaining_time":0.3384627518},
{"learn":[0.3181497651],"iteration":735,"passed_time":1.509585598,"remaining_time":0.3363750517},
{"learn":[0.318095181],"iteration":736,"passed_time":1.511469055,"remaining_time":0.3342869144},
{"learn":[0.3180945387],"iteration":737,"passed_time":1.512800407,"remaining_time":0.3320781381},
{"learn":[0.3180657765],"iteration":738,"passed_time":1.51465538,"remaining_time":0.3299858136},
{"learn":[0.3180389007],"iteration":739,"passed_time":1.516529338,"remaining_time":0.3278982353},
{"learn":[0.3179720601],"iteration":740,"passed_time":1.518359256,"remaining_time":0.3258017837},
{"learn":[0.3179700938],"iteration":741,"passed_time":1.520130798,"remaining_time":0.3236936201},
{"learn":[0.3178210597],"iteration":742,"passed_time":1.5219773,"remaining_time":0.321602202},
{"learn":[0.3177890048],"iteration":743,"passed_time":1.523830597,"remaining_time":0.3195128671},
{"learn":[0.3177633713],"iteration":744,"passed_time":1.525711749,"remaining_time":0.3174299613},
{"learn":[0.3176934815],"iteration":745,"passed_time":1.527516569,"remaining_time":0.3153318386},
{"learn":[0.3176523725],"iteration":746,"passed_time":1.52956543,"remaining_time":0.3132844857},
{"learn":[0.3175262519],"iteration":747,"passed_time":1.532180691,"remaining_time":0.3113522261},
{"learn":[0.317465886],"iteration":748,"passed_time":1.534182423,"remaining_time":0.3092944538},
{"learn":[0.3174496988],"iteration":749,"passed_time":1.536130858,"remaining_time":0.3072261716},
{"learn":[0.3173901405],"iteration":750,"passed_time":1.538319545,"remaining_time":0.305205875},
{"learn":[0.3173716048],"iteration":751,"passed_time":1.540432934,"remaining_time":0.3031703115},
{"learn":[0.3172286235],"iteration":752,"passed_time":1.542629726,"remaining_time":0.3011508231},
{"learn":[0.3171045046],"iteration":753,"passed_time":1.544750788,"remaining_time":0.2991162003},
{"learn":[0.3170910863],"iteration":754,"passed_time":1.546984591,"remaining_time":0.297103001},
{"learn":[0.3169501439],"iteration":755,"passed_time":1.549204862,"remaining_time":0.2950866403},
{"learn":[0.3168819002],"iteration":756,"passed_time":1.551349352,"remaining_time":0.2930554258},
{"learn":[0.3167199105],"iteration":757,"passed_time":1.553516092,"remaining_time":0.2910280806},
{"learn":[0.3166543921],"iteration":758,"passed_time":1.555706914,"remaining_time":0.2890048417},
{"learn":[0.3165445497],"iteration":759,"passed_time":1.557687835,"remaining_time":0.2869424959},
{"learn":[0.316502096],"iteration":760,"passed_time":1.559690172,"remaining_time":0.2848842759},
{"learn":[0.3164985052],"iteration":761,"passed_time":1.561708992,"remaining_time":0.2828291874},
{"learn":[0.3163404341],"iteration":762,"passed_time":1.56374984,"remaining_time":0.2807781496},
{"learn":[0.3163386296],"iteration":763,"passed_time":1.565685898,"remaining_time":0.2787084845},
{"learn":[0.3163376264],"iteration":764,"passed_time":1.567606063,"remaining_time":0.276636364},
{"learn":[0.3162206436],"iteration":765,"passed_time":1.569728035,"remaining_time":0.2745999435},
{"learn":[0.3162043372],"iteration":766,"passed_time":1.571730592,"remaining_time":0.2725425929},
{"learn":[0.3161555519],"iteration":767,"passed_time":1.573819313,"remaining_time":0.2705001945},
{"learn":[0.3161131415],"iteration":768,"passed_time":1.576050753,"remaining_time":0.2684819878},
{"learn":[0.3160095827],"iteration":769,"passed_time":1.577935361,"remaining_time":0.2664046714},
{"learn":[0.3159474176],"iteration":770,"passed_time":1.579943661,"remaining_time":0.2643485503},
{"learn":[0.3159303478],"iteration":771,"passed_time":1.581889131,"remaining_time":0.2622821357},
{"learn":[0.3159302072],"iteration":772,"passed_time":1.582894964,"remaining_time":0.2600616565},
{"learn":[0.3158839055],"iteration":773,"passed_time":1.585027424,"remaining_time":0.2580277202},
{"learn":[0.3158156802],"iteration":774,"passed_time":1.586975823,"remaining_time":0.2559638424},
{"learn":[0.315666149],"iteration":775,"passed_time":1.588874968,"remaining_time":0.2538923918},
{"learn":[0.3155397825],"iteration":776,"passed_time":1.590775681,"remaining_time":0.2518216329},
{"learn":[0.315536833],"iteration":777,"passed_time":1.592603764,"remaining_time":0.2497399218},
{"learn":[0.3153614068],"iteration":778,"passed_time":1.594562965,"remaining_time":0.2476792282},
{"learn":[0.3153585182],"iteration":779,"passed_time":1.596473976,"remaining_time":0.2456113809},
{"learn":[0.3152933795],"iteration":780,"passed_time":1.598456395,"remaining_time":0.2435548157},
{"learn":[0.3151952809],"iteration":781,"passed_time":1.600406878,"remaining_time":0.2414936209},
{"learn":[0.3151943566],"iteration":782,"passed_time":1.602243265,"remaining_time":0.2394156602},
{"learn":[0.3150466094],"iteration":783,"passed_time":1.604188376,"remaining_time":0.2373544025},
{"learn":[0.3148909771],"iteration":784,"passed_time":1.606016878,"remaining_time":0.2352763579},
{"learn":[0.3148150992],"iteration":785,"passed_time":1.60791215,"remaining_time":0.2332086324},
{"learn":[0.3147987908],"iteration":786,"passed_time":1.609847401,"remaining_time":0.2311470855},
{"learn":[0.3147499037],"iteration":787,"passed_time":1.611887648,"remaining_time":0.2291007825},
{"learn":[0.3146522092],"iteration":788,"passed_time":1.613784039,"remaining_time":0.2270342564},
{"learn":[0.3146258678],"iteration":789,"passed_time":1.615706713,"remaining_time":0.2249718208},
{"learn":[0.3146175632],"iteration":790,"passed_time":1.617494925,"remaining_time":0.2228912096},
{"learn":[0.3146162789],"iteration":791,"passed_time":1.619447878,"remaining_time":0.2208338015},
{"learn":[0.3145092348],"iteration":792,"passed_time":1.621702886,"remaining_time":0.2188174134},
{"learn":[0.3144930932],"iteration":793,"passed_time":1.62386469,"remaining_time":0.2167879813},
{"learn":[0.3144542103],"iteration":794,"passed_time":1.626078643,"remaining_time":0.2147651038},
{"learn":[0.3144455239],"iteration":795,"passed_time":1.628035989,"remaining_time":0.2127082197},
{"learn":[0.3144407489],"iteration":796,"passed_time":1.630160512,"remaining_time":0.2106731903},
{"learn":[0.3143405864],"iteration":797,"passed_time":1.632137704,"remaining_time":0.208619105},
{"learn":[0.3142544414],"iteration":798,"passed_time":1.634043558,"remaining_time":0.2065561944},
{"learn":[0.3142404014],"iteration":799,"passed_time":1.63589269,"remaining_time":0.2044865863},
{"learn":[0.3142251568],"iteration":800,"passed_time":1.637930071,"remaining_time":0.2024407953},
{"learn":[0.3142244741],"iteration":801,"passed_time":1.639549379,"remaining_time":0.2003439391},
{"learn":[0.3142034896],"iteration":802,"passed_time":1.641309405,"remaining_time":0.1982652706},
{"learn":[0.3140656434],"iteration":803,"passed_time":1.643394893,"remaining_time":0.1962262559},
{"learn":[0.3139510008],"iteration":804,"passed_time":1.645398104,"remaining_time":0.194177416},
{"learn":[0.3139327484],"iteration":805,"passed_time":1.647303029,"remaining_time":0.1921172267},
{"learn":[0.3137869283],"iteration":806,"passed_time":1.64932754,"remaining_time":0.1900712035},
{"learn":[0.3137772986],"iteration":807,"passed_time":1.651188445,"remaining_time":0.1880066051},
{"learn":[0.3137566184],"iteration":808,"passed_time":1.653102129,"remaining_time":0.1859484471},
{"learn":[0.3137363534],"iteration":809,"passed_time":1.65498376,"remaining_time":0.1838870845},
{"learn":[0.3137224941],"iteration":810,"passed_time":1.656961902,"remaining_time":0.1818367562},
{"learn":[0.3137219722],"iteration":811,"passed_time":1.658859396,"remaining_time":0.1797778656},
{"learn":[0.3136082065],"iteration":812,"passed_time":1.660951305,"remaining_time":0.1777401766},
{"learn":[0.3135610653],"iteration":813,"passed_time":1.662793082,"remaining_time":0.1756759275},
{"learn":[0.3135164729],"iteration":814,"passed_time":1.66465912,"remaining_time":0.1736147549},
{"learn":[0.3133832238],"iteration":815,"passed_time":1.666606686,"remaining_time":0.171562453},
{"learn":[0.3133825012],"iteration":816,"passed_time":1.66826867,"remaining_time":0.1694813949},
{"learn":[0.3133006621],"iteration":817,"passed_time":1.670209646,"remaining_time":0.1674293289},
{"learn":[0.3132792588],"iteration":818,"passed_time":1.672129114,"remaining_time":0.1653754069},
{"learn":[0.3131340184],"iteration":819,"passed_time":1.674058988,"remaining_time":0.1633228281},
{"learn":[0.3131265565],"iteration":820,"passed_time":1.675881501,"remaining_time":0.1612602176},
{"learn":[0.3130568867],"iteration":821,"passed_time":1.677866348,"remaining_time":0.1592135951},
{"learn":[0.3129668227],"iteration":822,"passed_time":1.679728764,"remaining_time":0.1571556681},
{"learn":[0.3129226635],"iteration":823,"passed_time":1.681595122,"remaining_time":0.1550985792},
{"learn":[0.3128884012],"iteration":824,"passed_time":1.683515248,"remaining_time":0.1530468407},
{"learn":[0.312807739],"iteration":825,"passed_time":1.685413498,"remaining_time":0.1509934611},
{"learn":[0.3126654392],"iteration":826,"passed_time":1.687188702,"remaining_time":0.1489295952},
{"learn":[0.3125948013],"iteration":827,"passed_time":1.689019776,"remaining_time":0.1468712848},
{"learn":[0.3124873263],"iteration":828,"passed_time":1.690920045,"remaining_time":0.144819449},
{"learn":[0.3124322763],"iteration":829,"passed_time":1.6929599,"remaining_time":0.1427797506},
{"learn":[0.3123685544],"iteration":830,"passed_time":1.694905919,"remaining_time":0.1407322604},
{"learn":[0.3122265322],"iteration":831,"passed_time":1.69679893,"remaining_time":0.1386806818},
{"learn":[0.3122120879],"iteration":832,"passed_time":1.698714867,"remaining_time":0.1366313279},
{"learn":[0.3121682397],"iteration":833,"passed_time":1.700900346,"remaining_time":0.1346036245},
{"learn":[0.3120972765],"iteration":834,"passed_time":1.70283032,"remaining_time":0.1325556536},
{"learn":[0.312071017],"iteration":835,"passed_time":1.704770953,"remaining_time":0.1305087811},
{"learn":[0.3120318982],"iteration":836,"passed_time":1.706695025,"remaining_time":0.1284609159},
{"learn":[0.3118909696],"iteration":837,"passed_time":1.708612223,"remaining_time":0.1264128375},
{"learn":[0.3118599771],"iteration":838,"passed_time":1.710523943,"remaining_time":0.1243646729},
{"learn":[0.3118028032],"iteration":839,"passed_time":1.71240702,"remaining_time":0.1223147871},
{"learn":[0.3116957308],"iteration":840,"passed_time":1.714301613,"remaining_time":0.1202661061},
{"learn":[0.3116559445],"iteration":841,"passed_time":1.716213732,"remaining_time":0.1182189982},
{"learn":[0.3116543199],"iteration":842,"passed_time":1.717985556,"remaining_time":0.1161627244},
{"learn":[0.311645636],"iteration":843,"passed_time":1.71976755,"remaining_time":0.1141077995},
{"learn":[0.3115053301],"iteration":844,"passed_time":1.721718918,"remaining_time":0.112064545},
{"learn":[0.3114149261],"iteration":845,"passed_time":1.723637289,"remaining_time":0.1100194014},
{"learn":[0.3114070222],"iteration":846,"passed_time":1.725679001,"remaining_time":0.1079822751},
{"learn":[0.3114034111],"iteration":847,"passed_time":1.727616961,"remaining_time":0.1059387759},
{"learn":[0.3112639056],"iteration":848,"passed_time":1.729723117,"remaining_time":0.1039056289},
{"learn":[0.3112619997],"iteration":849,"passed_time":1.731531645,"remaining_time":0.1018548026},
{"learn":[0.3111925477],"iteration":850,"passed_time":1.733406019,"remaining_time":0.09980833714},
{"learn":[0.310987798],"iteration":851,"passed_time":1.735304422,"remaining_time":0.0977636294},
{"learn":[0.3109869149],"iteration":852,"passed_time":1.737094767,"remaining_time":0.09571331072},
{"learn":[0.310964209],"iteration":853,"passed_time":1.739002114,"remaining_time":0.09366990309},
{"learn":[0.3109141032],"iteration":854,"passed_time":1.740912864,"remaining_time":0.09162699283},
{"learn":[0.3107904734],"iteration":855,"passed_time":1.74272677,"remaining_time":0.08957941342},
{"learn":[0.3107479912],"iteration":856,"passed_time":1.74471391,"remaining_time":0.08754107135},
{"learn":[0.3107335466],"iteration":857,"passed_time":1.746526672,"remaining_time":0.0854943126},
{"learn":[0.3105794718],"iteration":858,"passed_time":1.748430938,"remaining_time":0.0834524662},
{"learn":[0.3105607766],"iteration":859,"passed_time":1.750247314,"remaining_time":0.08140685179},
{"learn":[0.3105388697],"iteration":860,"passed_time":1.75213841,"remaining_time":0.07936515445},
{"learn":[0.3104773722],"iteration":861,"passed_time":1.753995598,"remaining_time":0.07732231175},
{"learn":[0.3104662182],"iteration":862,"passed_time":1.755926894,"remaining_time":0.07528307657},
{"learn":[0.3103273264],"iteration":863,"passed_time":1.757713437,"remaining_time":0.07323805986},
{"learn":[0.3103112187],"iteration":864,"passed_time":1.759642425,"remaining_time":0.07119940446},
{"learn":[0.310310757],"iteration":865,"passed_time":1.760822019,"remaining_time":0.06913158042},
{"learn":[0.3102804801],"iteration":866,"passed_time":1.762649638,"remaining_time":0.06709047064},
{"learn":[0.3102800984],"iteration":867,"passed_time":1.764407344,"remaining_time":0.06504727535},
{"learn":[0.3101928895],"iteration":868,"passed_time":1.766336026,"remaining_time":0.06301083636},
{"learn":[0.3101891976],"iteration":869,"passed_time":1.768140148,"remaining_time":0.06097034995},
{"learn":[0.3100890932],"iteration":870,"passed_time":1.770203137,"remaining_time":0.05893902524},
{"learn":[0.3099434524],"iteration":871,"passed_time":1.772099198,"remaining_time":0.05690226783},
{"learn":[0.3098139259],"iteration":872,"passed_time":1.773952952,"remaining_time":0.05486452428},
{"learn":[0.3097685104],"iteration":873,"passed_time":1.775830613,"remaining_time":0.05282791296},
{"learn":[0.3096338203],"iteration":874,"passed_time":1.777786222,"remaining_time":0.05079389205},
{"learn":[0.3095253105],"iteration":875,"passed_time":1.779686531,"remaining_time":0.04875853509},
{"learn":[0.3094282007],"iteration":876,"passed_time":1.78154264,"remaining_time":0.04672232694},
{"learn":[0.3093276385],"iteration":877,"passed_time":1.78351036,"remaining_time":0.04468932566},
{"learn":[0.3092410981],"iteration":878,"passed_time":1.785268076,"remaining_time":0.04265145575},
{"learn":[0.3092232054],"iteration":879,"passed_time":1.787199994,"remaining_time":0.04061818167},
{"learn":[0.3092139173],"iteration":880,"passed_time":1.789160898,"remaining_time":0.03858576284},
{"learn":[0.3092065168],"iteration":881,"passed_time":1.791054042,"remaining_time":0.03655212331},
{"learn":[0.3091684356],"iteration":882,"passed_time":1.792944681,"remaining_time":0.03451875377},
{"learn":[0.3091430024],"iteration":883,"passed_time":1.794860527,"remaining_time":0.03248616338},
{"learn":[0.3091397921],"iteration":884,"passed_time":1.796778002,"remaining_time":0.03045386443},
{"learn":[0.3091303637],"iteration":885,"passed_time":1.798630418,"remaining_time":0.02842079667},
{"learn":[0.3090431878],"iteration":886,"passed_time":1.800489423,"remaining_time":0.0263882328},
{"learn":[0.3089629881],"iteration":887,"passed_time":1.802466392,"remaining_time":0.02435765394},
{"learn":[0.3089118186],"iteration":888,"passed_time":1.8043689,"remaining_time":0.02232627435},
{"learn":[0.3087663951],"iteration":889,"passed_time":1.806305168,"remaining_time":0.02029556368},
{"learn":[0.3087084447],"iteration":890,"passed_time":1.808233629,"remaining_time":0.01826498615},
{"learn":[0.3086793954],"iteration":891,"passed_time":1.81025084,"remaining_time":0.01623543354},
{"learn":[0.3086038287],"iteration":892,"passed_time":1.812134115,"remaining_time":0.01420485868},
{"learn":[0.308582003],"iteration":893,"passed_time":1.814073243,"remaining_time":0.01217498821},
{"learn":[0.3085802367],"iteration":894,"passed_time":1.815979547,"remaining_time":0.01014513713},
{"learn":[0.3085382519],"iteration":895,"passed_time":1.817820162,"remaining_time":0.00811526858},
{"learn":[0.3084625615],"iteration":896,"passed_time":1.819619551,"remaining_time":0.006085684117},
{"learn":[0.3084618397],"iteration":897,"passed_time":1.821343002,"remaining_time":0.004056443212},
{"learn":[0.3084242052],"iteration":898,"passed_time":1.823262928,"remaining_time":0.002028101143},
{"learn":[0.3084221186],"iteration":899,"passed_time":1.825107055,"remaining_time":0}
]}